ALU_unit.sv
module ALU_unit #(
    parameter WIDTH = 32
)(
    input   logic [WIDTH-1:0] ALUop1,
    input   logic [WIDTH-1:0] RegOp2,
    input   logic [WIDTH-1:0] ImmOp,
    output  logic [WIDTH-1:0] ALUout,
    input   logic [2:0]       ALUctrl,
    input   logic             ALUsrc,
    output  logic             EQ
);

logic [WIDTH-1:0] ALUop2;

always_comb begin
    ALUop2 = ALUsrc ? ImmOp : RegOp2;
    ALUout = ALUctrl[0] ? ALUop1 - ALUop2 : ALUop1 + ALUop2;
    EQ = (ALUop1 == ALUop2);
end

endmodule

signextend.sv
module signextend #(
    parameter Width = 32
)(
    input  logic [Width-1:0] instr,
    input  logic             ImmSrc,  //should be instr[4]
    output logic [Width-1:0] ImmOp
);


assign ImmOp = ImmSrc ? { {20{instr[31]}}, instr[31:20] } : { {20{instr[31]}}, instr[31], instr[7], instr[30:25], instr[11:8], 1'b0 }; //{instr[31], instr[7], instr[30:25], instr[11:8]};     

    // assign a = {20'hFFFFF, instr}
    // assign b = {20'h0, instr}  
   

    // assign ImmOp = ImmSrc ? a : b;
endmodule

RegFile.sv
module RegFile #(
    parameter D_WIDTH = 32,
              A_WIDTH = 5
)(
    input logic clk,
    input logic WE3,
    input logic [A_WIDTH-1:0] AD1,
    input logic [A_WIDTH-1:0] AD2,
    input logic [A_WIDTH-1:0] AD3,
    input logic [D_WIDTH-1:0] WD3,
    output logic [D_WIDTH-1:0] RD1,
    output logic [D_WIDTH-1:0] RD2,
    output logic [D_WIDTH-1:0] a0
);

reg [D_WIDTH-1:0] reg_file [31:0];



// initial begin
//     // for (i = 0; i < 2**A_WIDTH -1; i++){
//     //     reg_file[i] <= 32'b0
//     // }
//     $display("Loading RegFile.");
//     $readmemh("RegFile.mem", reg_file);
// end;
assign reg_file[0] = 32'b0;

always_ff @( posedge clk ) begin 

    if (WE3) reg_file[AD3] = WD3;
    
end

always_comb begin
    RD1 = reg_file[AD1];
    RD2 = reg_file[AD2];
    a0 <= reg_file[0];
end

endmodule

control_unit.sv
module control_unit #(
    parameter Wid = 32
)(
    input  logic           EQ,
    input  logic [Wid-1:0] instr,
    output logic           RegWrite,
    output logic           ALUsrc,
    output logic           PCsrc,
    output logic [2:0]     ALUctrl,
    output logic           ImmSrc
);

always_comb

    case(instr[6:0])

    7'b0010011:begin //addi
    ALUctrl = instr[14:12];
    RegWrite = 1;
    ImmSrc = 1;
    ALUsrc = 1;
    PCsrc = 0;
    end

    7'b1100011:begin //bne
    ALUctrl = instr[14:12];
    RegWrite = 0;
    PCsrc = ~EQ;   
    ImmSrc = 0;
    ALUsrc = 0;
    end

    7'b0000011:begin //load
    ALUctrl = instr[14:12];
    RegWrite = 1;
    ImmSrc = 1;
    ALUsrc = 1;
    PCsrc = 0;
    end

    default:begin
    ALUctrl = instr[14:12];
    ImmSrc = 1;
    PCsrc = 0;
    RegWrite = 0;
    ALUsrc = 0;
    end

    endcase





    // begin                        // add      0110011
    // PCsrc = instr[6];            //addi      0010011
    // ALUsrc = ~instr[6];           //branch    1100011
    // ALUctrl = instr[14:12];      //          ||^ PCsrc
    // RegWrite = ~instr[6];        //          |^   not ALUsrc
    // ImmSrc = instr[6];          //          ^ not RegWrite 
    // end                          //          ALUctrl: funct3

endmodule





// 000 0011 load
// 001 0011 addi
// 110 0011 bne
// ^^ ~RegWrite
// ^^ PCsrc
// ^^ ~ALUsrc
// ^^ ~Immsrc

instr_rom.sv
module instr_rom 
// #(
//     parameter ADDRESS_WIDTH = 32, //should be in the same length as PC
//               DATA_WIDTH    = 8)
(
    input logic  [31:0]     addr,
    output logic [31:0]     dout

);

logic [7:0] rom_array [2**8-1:0]; //Theoretically, there should be 2^32 in memmory   
logic [7:0] short_addr;                 // but we do not need that many space, so I made to 
                                            // have only 256 memory spaces
//date width should be 8bit because it is a byte addressable memory
//so each instruction consist of four 8-bit byte

initial begin
        $display("Loading Instr_mem.");
        $readmemh("instruction.mem", rom_array);  //read instruction into rom
        // $display(rom_array [0], rom_array [1], rom_array [2],rom_array [3]);
end;

always_comb
    dout <= {rom_array [short_addr[7:0]+3], rom_array [short_addr[7:0]+2], rom_array [short_addr[7:0]+1],rom_array [short_addr[7:0]]};
    // dout <= 8'h11;

endmodule

counter_unit.sv
module counter_unit #(
    parameter PC_WIDTH = 32 // the length of pc and imme
)(
    input  logic clk,
    input  logic rst,
    input  logic PCsrc,
    // input  logic [PC_WIDTH-1:0] PC,
    input  logic [PC_WIDTH-1:0] ImmOp,
    output logic [PC_WIDTH-1:0] PC
);

// logic [PC_WIDTH-1:0] next_PC;
// logic [PC_WIDTH-1:0] branch_PC;

// assign branch_PC = PC + ImmOp;                                        //compute branch_pc
// assign next_PC = PCsrc ? branch_PC : PC + {{PC_WIDTH-1{1'b0}}, 1'b1};    //compute inc_PC

always_ff @ (posedge clk)begin
  if (rst)           PC <= 32'hBFC00000;
  else PC <= PCsrc ? PC + ImmOp : PC + 4;
  // else if (PCsrc)    PC <= PC + ImmOp;
  // else               PC <= PC + 4;
end


endmodule

top.sv
module top #(
    parameter D_WIDTH = 32,
              A_WIDTH = 5
)(
    input  logic        clk,
    input  logic        rst,
    output logic [16:0] a0
);

logic [D_WIDTH-1:0] PC;
logic [D_WIDTH-1:0] ImmOp;
logic PCsrc;
logic EQ;
logic RegWrite;
logic ALUctrl;
logic ALUsrc;
logic ImmSrc;
logic [A_WIDTH-1:0] AD1;
logic [A_WIDTH-1:0] AD2;
logic [A_WIDTH-1:0] AD3;
logic [A_WIDTH-1:0] WD3;
logic [D_WIDTH-1:0] RD1;
logic [D_WIDTH-1:0] RD2;
logic [D_WIDTH-1:0] ALUout;
logic [D_WIDTH-1:0] instr;
logic [D_WIDTH-1:0] out;


counter_unit pc_counter(
    .clk(clk),
    .rst(rst),
    .PCsrc(PCsrc),
    .ImmOp(ImmOp),
    .PC(PC)
);

instr_rom instr_mem(
    .addr(PC),
    .dout(instr)
);

control_unit encoder(
    .EQ(EQ),
    .instr(instr),
    .RegWrite(RegWrite),
    .ALUsrc(ALUsrc),
    .PCsrc(PCsrc),
    .ALUctrl(ALUctrl),
    .ImmSrc(ImmSrc)
);

RegFile register_file(
    .clk(clk),
    .WE3(RegWrite),
    .AD1(instr[19:15]),
    .AD2(instr[24:20]),
    .AD3(instr[11:7]),
    .RD1(RD1),
    .RD2(RD2),
    .WD3(ALUout),
    .a0(a0)
);

signextend extend(
    .instr(instr),
    .ImmSrc(ImmSrc),
    .ImmOp(ImmOp)
);

ALU_unit ALU(
    .ALUop1(RD1),
    .RegOp2(RD2),
    .ImmOp(ImmOp),
    .ALUctrl(ALUctrl),
    .ALUout(ALUout),
    .ALUsrc(ALUsrc),
    .EQ(EQ)
);



endmodule

top.vcd
$version Generated by VerilatedVcd $end
$date Tue Nov 22 18:30:00 2022 $end
$timescale 1ps $end

 $scope module TOP $end
  $var wire 17 Y a0 [16:0] $end
  $var wire  1 W clk $end
  $var wire  1 X rst $end
  $scope module top $end
   $var wire  5 \ AD1 [4:0] $end
   $var wire  5 ] AD2 [4:0] $end
   $var wire  5 ^ AD3 [4:0] $end
   $var wire  1 ( ALUctrl $end
   $var wire 32 - ALUout [31:0] $end
   $var wire  1 ) ALUsrc $end
   $var wire 32 [ A_WIDTH [31:0] $end
   $var wire 32 Z D_WIDTH [31:0] $end
   $var wire  1 & EQ $end
   $var wire 32 $ ImmOp [31:0] $end
   $var wire  1 * ImmSrc $end
   $var wire 32 # PC [31:0] $end
   $var wire  1 % PCsrc $end
   $var wire 32 + RD1 [31:0] $end
   $var wire 32 , RD2 [31:0] $end
   $var wire  1 ' RegWrite $end
   $var wire  5 _ WD3 [4:0] $end
   $var wire 17 Y a0 [16:0] $end
   $var wire  1 W clk $end
   $var wire 32 . instr [31:0] $end
   $var wire 32 ` out [31:0] $end
   $var wire  1 X rst $end
   $scope module ALU $end
    $var wire  3 / ALUctrl [2:0] $end
    $var wire 32 + ALUop1 [31:0] $end
    $var wire 32 0 ALUop2 [31:0] $end
    $var wire 32 - ALUout [31:0] $end
    $var wire  1 ) ALUsrc $end
    $var wire  1 & EQ $end
    $var wire 32 $ ImmOp [31:0] $end
    $var wire 32 , RegOp2 [31:0] $end
    $var wire 32 Z WIDTH [31:0] $end
   $upscope $end
   $scope module encoder $end
    $var wire  3 1 ALUctrl [2:0] $end
    $var wire  1 ) ALUsrc $end
    $var wire  1 & EQ $end
    $var wire  1 * ImmSrc $end
    $var wire  1 % PCsrc $end
    $var wire  1 ' RegWrite $end
    $var wire 32 Z Wid [31:0] $end
    $var wire 32 . instr [31:0] $end
   $upscope $end
   $scope module extend $end
    $var wire 32 $ ImmOp [31:0] $end
    $var wire  1 * ImmSrc $end
    $var wire 32 Z Width [31:0] $end
    $var wire 32 . instr [31:0] $end
   $upscope $end
   $scope module instr_mem $end
    $var wire 32 # addr [31:0] $end
    $var wire 32 . dout [31:0] $end
    $var wire  8 2 short_addr [7:0] $end
   $upscope $end
   $scope module pc_counter $end
    $var wire 32 $ ImmOp [31:0] $end
    $var wire 32 # PC [31:0] $end
    $var wire 32 Z PC_WIDTH [31:0] $end
    $var wire  1 % PCsrc $end
    $var wire  1 W clk $end
    $var wire  1 X rst $end
   $upscope $end
   $scope module register_file $end
    $var wire  5 3 AD1 [4:0] $end
    $var wire  5 4 AD2 [4:0] $end
    $var wire  5 5 AD3 [4:0] $end
    $var wire 32 [ A_WIDTH [31:0] $end
    $var wire 32 Z D_WIDTH [31:0] $end
    $var wire 32 + RD1 [31:0] $end
    $var wire 32 , RD2 [31:0] $end
    $var wire 32 - WD3 [31:0] $end
    $var wire  1 ' WE3 $end
    $var wire 32 6 a0 [31:0] $end
    $var wire  1 W clk $end
    $var wire 32 7 reg_file[0] [31:0] $end
    $var wire 32 A reg_file[10] [31:0] $end
    $var wire 32 B reg_file[11] [31:0] $end
    $var wire 32 C reg_file[12] [31:0] $end
    $var wire 32 D reg_file[13] [31:0] $end
    $var wire 32 E reg_file[14] [31:0] $end
    $var wire 32 F reg_file[15] [31:0] $end
    $var wire 32 G reg_file[16] [31:0] $end
    $var wire 32 H reg_file[17] [31:0] $end
    $var wire 32 I reg_file[18] [31:0] $end
    $var wire 32 J reg_file[19] [31:0] $end
    $var wire 32 8 reg_file[1] [31:0] $end
    $var wire 32 K reg_file[20] [31:0] $end
    $var wire 32 L reg_file[21] [31:0] $end
    $var wire 32 M reg_file[22] [31:0] $end
    $var wire 32 N reg_file[23] [31:0] $end
    $var wire 32 O reg_file[24] [31:0] $end
    $var wire 32 P reg_file[25] [31:0] $end
    $var wire 32 Q reg_file[26] [31:0] $end
    $var wire 32 R reg_file[27] [31:0] $end
    $var wire 32 S reg_file[28] [31:0] $end
    $var wire 32 T reg_file[29] [31:0] $end
    $var wire 32 9 reg_file[2] [31:0] $end
    $var wire 32 U reg_file[30] [31:0] $end
    $var wire 32 V reg_file[31] [31:0] $end
    $var wire 32 : reg_file[3] [31:0] $end
    $var wire 32 ; reg_file[4] [31:0] $end
    $var wire 32 < reg_file[5] [31:0] $end
    $var wire 32 = reg_file[6] [31:0] $end
    $var wire 32 > reg_file[7] [31:0] $end
    $var wire 32 ? reg_file[8] [31:0] $end
    $var wire 32 @ reg_file[9] [31:0] $end
   $upscope $end
  $upscope $end
 $upscope $end
$enddefinitions $end


#0
b00000000000000000000000000000000 #
b00000000000000000000000000000000 $
0%
0&
0'
0(
0)
0*
b00000000000000000000000000000000 +
b00000000000000000000000000000000 ,
b00000000000000000000000000000000 -
b00000000000000000000000000000000 .
b000 /
b00000000000000000000000000000000 0
b000 1
b00000000 2
b00000 3
b00000 4
b00000 5
b00000000000000000000000000000000 6
b00000000000000000000000000000000 7
b00000000000000000000000000000000 8
b00000000000000000000000000000000 9
b00000000000000000000000000000000 :
b00000000000000000000000000000000 ;
b00000000000000000000000000000000 <
b00000000000000000000000000000000 =
b00000000000000000000000000000000 >
b00000000000000000000000000000000 ?
b00000000000000000000000000000000 @
b00000000000000000000000000000000 A
b00000000000000000000000000000000 B
b00000000000000000000000000000000 C
b00000000000000000000000000000000 D
b00000000000000000000000000000000 E
b00000000000000000000000000000000 F
b00000000000000000000000000000000 G
b00000000000000000000000000000000 H
b00000000000000000000000000000000 I
b00000000000000000000000000000000 J
b00000000000000000000000000000000 K
b00000000000000000000000000000000 L
b00000000000000000000000000000000 M
b00000000000000000000000000000000 N
b00000000000000000000000000000000 O
b00000000000000000000000000000000 P
b00000000000000000000000000000000 Q
b00000000000000000000000000000000 R
b00000000000000000000000000000000 S
b00000000000000000000000000000000 T
b00000000000000000000000000000000 U
b00000000000000000000000000000000 V
0W
0X
b00000000000000000 Y
b00000000000000000000000000100000 Z
b00000000000000000000000000000101 [
b00000 \
b00000 ]
b00000 ^
b00000 _
b00000000000000000000000000000000 `
#1
b00000000000000000000000000010001 $
1'
1)
1*
b00000000000000000000000000010001 -
b00000001000100000000001100010011 .
b00000000000000000000000000010001 0
b10001 4
b00110 5
1W
#2
0W
1X
#3
b00000000000000000000000000010001 =
1W
#4
0W
0X
#5
b00000000000000000000000000000100 #
b00000000000000000000000000000000 $
1&
b00000000000000000000000000000000 -
b00000000000000000000010100010011 .
b00000000000000000000000000000000 0
b00000100 2
b00000 4
b01010 5
1W
#6
0W
#7
b00000000000000000000000000001000 #
b00000000000000000000010110010011 .
b00001000 2
b01011 5
1W
#8
0W
#9
b00000000000000000000000000001100 #
b00000000000001011000010100010011 .
b00001100 2
b01011 3
b01010 5
1W
#10
0W
#11
b00000000000000000000000000010000 #
b00000000000000000000000000000001 $
0&
b00000000000000000000000000000001 -
b00000000000101011000010110010011 .
b00000000000000000000000000000001 0
b00010000 2
b00001 4
b01011 5
1W
#12
0W
#13
b00000000000000000000000000010100 #
b11111111111111111111111111111000 $
1%
0'
1(
0)
0*
b00000000000000000000000000000001 +
b00000000000000000000000000010001 ,
b11111111111111111111111111110000 -
b11111110011001011001110011100011 .
b001 /
b00000000000000000000000000010001 0
b001 1
b00010100 2
b00110 4
b11001 5
b00000000000000000000000000000001 B
1W
#14
0W
#15
b00000000000000000000000000001100 #
b00000000000000000000000000000000 $
0%
1'
0(
1)
1*
b00000000000000000000000000000000 ,
b00000000000000000000000000000001 -
b00000000000001011000010100010011 .
b000 /
b00000000000000000000000000000000 0
b000 1
b00001100 2
b00000 4
b01010 5
1W
#16
0W
#17
b00000000000000000000000000010000 #
b00000000000000000000000000000001 $
1&
b00000000000000000000000000000010 -
b00000000000101011000010110010011 .
b00000000000000000000000000000001 0
b00010000 2
b00001 4
b01011 5
b00000000000000000000000000000001 A
1W
#18
0W
#19
b00000000000000000000000000010100 #
b11111111111111111111111111111000 $
1%
0&
0'
1(
0)
0*
b00000000000000000000000000000010 +
b00000000000000000000000000010001 ,
b11111111111111111111111111110001 -
b11111110011001011001110011100011 .
b001 /
b00000000000000000000000000010001 0
b001 1
b00010100 2
b00110 4
b11001 5
b00000000000000000000000000000010 B
1W
#20
0W
#21
b00000000000000000000000000001100 #
b00000000000000000000000000000000 $
0%
1'
0(
1)
1*
b00000000000000000000000000000000 ,
b00000000000000000000000000000010 -
b00000000000001011000010100010011 .
b000 /
b00000000000000000000000000000000 0
b000 1
b00001100 2
b00000 4
b01010 5
1W
#22
0W
#23
b00000000000000000000000000010000 #
b00000000000000000000000000000001 $
b00000000000000000000000000000011 -
b00000000000101011000010110010011 .
b00000000000000000000000000000001 0
b00010000 2
b00001 4
b01011 5
b00000000000000000000000000000010 A
1W
#24
0W
#25
b00000000000000000000000000010100 #
b11111111111111111111111111111000 $
1%
0'
1(
0)
0*
b00000000000000000000000000000011 +
b00000000000000000000000000010001 ,
b11111111111111111111111111110010 -
b11111110011001011001110011100011 .
b001 /
b00000000000000000000000000010001 0
b001 1
b00010100 2
b00110 4
b11001 5
b00000000000000000000000000000011 B
1W
#26
0W
#27
b00000000000000000000000000001100 #
b00000000000000000000000000000000 $
0%
1'
0(
1)
1*
b00000000000000000000000000000000 ,
b00000000000000000000000000000011 -
b00000000000001011000010100010011 .
b000 /
b00000000000000000000000000000000 0
b000 1
b00001100 2
b00000 4
b01010 5
1W
#28
0W
#29
b00000000000000000000000000010000 #
b00000000000000000000000000000001 $
b00000000000000000000000000000100 -
b00000000000101011000010110010011 .
b00000000000000000000000000000001 0
b00010000 2
b00001 4
b01011 5
b00000000000000000000000000000011 A
1W
#30
0W
#31
b00000000000000000000000000010100 #
b11111111111111111111111111111000 $
1%
0'
1(
0)
0*
b00000000000000000000000000000100 +
b00000000000000000000000000010001 ,
b11111111111111111111111111110011 -
b11111110011001011001110011100011 .
b001 /
b00000000000000000000000000010001 0
b001 1
b00010100 2
b00110 4
b11001 5
b00000000000000000000000000000100 B
1W
#32
0W
#33
b00000000000000000000000000001100 #
b00000000000000000000000000000000 $
0%
1'
0(
1)
1*
b00000000000000000000000000000000 ,
b00000000000000000000000000000100 -
b00000000000001011000010100010011 .
b000 /
b00000000000000000000000000000000 0
b000 1
b00001100 2
b00000 4
b01010 5
1W
#34
0W
#35
b00000000000000000000000000010000 #
b00000000000000000000000000000001 $
b00000000000000000000000000000101 -
b00000000000101011000010110010011 .
b00000000000000000000000000000001 0
b00010000 2
b00001 4
b01011 5
b00000000000000000000000000000100 A
1W
#36
0W
#37
b00000000000000000000000000010100 #
b11111111111111111111111111111000 $
1%
0'
1(
0)
0*
b00000000000000000000000000000101 +
b00000000000000000000000000010001 ,
b11111111111111111111111111110100 -
b11111110011001011001110011100011 .
b001 /
b00000000000000000000000000010001 0
b001 1
b00010100 2
b00110 4
b11001 5
b00000000000000000000000000000101 B
1W
#38
0W
#39
b00000000000000000000000000001100 #
b00000000000000000000000000000000 $
0%
1'
0(
1)
1*
b00000000000000000000000000000000 ,
b00000000000000000000000000000101 -
b00000000000001011000010100010011 .
b000 /
b00000000000000000000000000000000 0
b000 1
b00001100 2
b00000 4
b01010 5
1W
#40
0W
#41
b00000000000000000000000000010000 #
b00000000000000000000000000000001 $
b00000000000000000000000000000110 -
b00000000000101011000010110010011 .
b00000000000000000000000000000001 0
b00010000 2
b00001 4
b01011 5
b00000000000000000000000000000101 A
1W
#42
0W
#43
b00000000000000000000000000010100 #
b11111111111111111111111111111000 $
1%
0'
1(
0)
0*
b00000000000000000000000000000110 +
b00000000000000000000000000010001 ,
b11111111111111111111111111110101 -
b11111110011001011001110011100011 .
b001 /
b00000000000000000000000000010001 0
b001 1
b00010100 2
b00110 4
b11001 5
b00000000000000000000000000000110 B
1W
#44
0W
#45
b00000000000000000000000000001100 #
b00000000000000000000000000000000 $
0%
1'
0(
1)
1*
b00000000000000000000000000000000 ,
b00000000000000000000000000000110 -
b00000000000001011000010100010011 .
b000 /
b00000000000000000000000000000000 0
b000 1
b00001100 2
b00000 4
b01010 5
1W
#46
0W
#47
b00000000000000000000000000010000 #
b00000000000000000000000000000001 $
b00000000000000000000000000000111 -
b00000000000101011000010110010011 .
b00000000000000000000000000000001 0
b00010000 2
b00001 4
b01011 5
b00000000000000000000000000000110 A
1W
#48
0W
#49
b00000000000000000000000000010100 #
b11111111111111111111111111111000 $
1%
0'
1(
0)
0*
b00000000000000000000000000000111 +
b00000000000000000000000000010001 ,
b11111111111111111111111111110110 -
b11111110011001011001110011100011 .
b001 /
b00000000000000000000000000010001 0
b001 1
b00010100 2
b00110 4
b11001 5
b00000000000000000000000000000111 B
1W
#50
0W
#51
b00000000000000000000000000001100 #
b00000000000000000000000000000000 $
0%
1'
0(
1)
1*
b00000000000000000000000000000000 ,
b00000000000000000000000000000111 -
b00000000000001011000010100010011 .
b000 /
b00000000000000000000000000000000 0
b000 1
b00001100 2
b00000 4
b01010 5
1W
#52
0W
#53
b00000000000000000000000000010000 #
b00000000000000000000000000000001 $
b00000000000000000000000000001000 -
b00000000000101011000010110010011 .
b00000000000000000000000000000001 0
b00010000 2
b00001 4
b01011 5
b00000000000000000000000000000111 A
1W
#54
0W
#55
b00000000000000000000000000010100 #
b11111111111111111111111111111000 $
1%
0'
1(
0)
0*
b00000000000000000000000000001000 +
b00000000000000000000000000010001 ,
b11111111111111111111111111110111 -
b11111110011001011001110011100011 .
b001 /
b00000000000000000000000000010001 0
b001 1
b00010100 2
b00110 4
b11001 5
b00000000000000000000000000001000 B
1W
#56
0W
#57
b00000000000000000000000000001100 #
b00000000000000000000000000000000 $
0%
1'
0(
1)
1*
b00000000000000000000000000000000 ,
b00000000000000000000000000001000 -
b00000000000001011000010100010011 .
b000 /
b00000000000000000000000000000000 0
b000 1
b00001100 2
b00000 4
b01010 5
1W
#58
0W
#59
b00000000000000000000000000010000 #
b00000000000000000000000000000001 $
b00000000000000000000000000001001 -
b00000000000101011000010110010011 .
b00000000000000000000000000000001 0
b00010000 2
b00001 4
b01011 5
b00000000000000000000000000001000 A
1W
#60
0W
#61
b00000000000000000000000000010100 #
b11111111111111111111111111111000 $
1%
0'
1(
0)
0*
b00000000000000000000000000001001 +
b00000000000000000000000000010001 ,
b11111111111111111111111111111000 -
b11111110011001011001110011100011 .
b001 /
b00000000000000000000000000010001 0
b001 1
b00010100 2
b00110 4
b11001 5
b00000000000000000000000000001001 B
1W
#62
0W
#63
b00000000000000000000000000001100 #
b00000000000000000000000000000000 $
0%
1'
0(
1)
1*
b00000000000000000000000000000000 ,
b00000000000000000000000000001001 -
b00000000000001011000010100010011 .
b000 /
b00000000000000000000000000000000 0
b000 1
b00001100 2
b00000 4
b01010 5
1W
#64
0W
#65
b00000000000000000000000000010000 #
b00000000000000000000000000000001 $
b00000000000000000000000000001010 -
b00000000000101011000010110010011 .
b00000000000000000000000000000001 0
b00010000 2
b00001 4
b01011 5
b00000000000000000000000000001001 A
1W
#66
0W
#67
b00000000000000000000000000010100 #
b11111111111111111111111111111000 $
1%
0'
1(
0)
0*
b00000000000000000000000000001010 +
b00000000000000000000000000010001 ,
b11111111111111111111111111111001 -
b11111110011001011001110011100011 .
b001 /
b00000000000000000000000000010001 0
b001 1
b00010100 2
b00110 4
b11001 5
b00000000000000000000000000001010 B
1W
#68
0W
#69
b00000000000000000000000000001100 #
b00000000000000000000000000000000 $
0%
1'
0(
1)
1*
b00000000000000000000000000000000 ,
b00000000000000000000000000001010 -
b00000000000001011000010100010011 .
b000 /
b00000000000000000000000000000000 0
b000 1
b00001100 2
b00000 4
b01010 5
1W
#70
0W
#71
b00000000000000000000000000010000 #
b00000000000000000000000000000001 $
b00000000000000000000000000001011 -
b00000000000101011000010110010011 .
b00000000000000000000000000000001 0
b00010000 2
b00001 4
b01011 5
b00000000000000000000000000001010 A
1W
#72
0W
#73
b00000000000000000000000000010100 #
b11111111111111111111111111111000 $
1%
0'
1(
0)
0*
b00000000000000000000000000001011 +
b00000000000000000000000000010001 ,
b11111111111111111111111111111010 -
b11111110011001011001110011100011 .
b001 /
b00000000000000000000000000010001 0
b001 1
b00010100 2
b00110 4
b11001 5
b00000000000000000000000000001011 B
1W
#74
0W
#75
b00000000000000000000000000001100 #
b00000000000000000000000000000000 $
0%
1'
0(
1)
1*
b00000000000000000000000000000000 ,
b00000000000000000000000000001011 -
b00000000000001011000010100010011 .
b000 /
b00000000000000000000000000000000 0
b000 1
b00001100 2
b00000 4
b01010 5
1W
#76
0W
#77
b00000000000000000000000000010000 #
b00000000000000000000000000000001 $
b00000000000000000000000000001100 -
b00000000000101011000010110010011 .
b00000000000000000000000000000001 0
b00010000 2
b00001 4
b01011 5
b00000000000000000000000000001011 A
1W
#78
0W
#79
b00000000000000000000000000010100 #
b11111111111111111111111111111000 $
1%
0'
1(
0)
0*
b00000000000000000000000000001100 +
b00000000000000000000000000010001 ,
b11111111111111111111111111111011 -
b11111110011001011001110011100011 .
b001 /
b00000000000000000000000000010001 0
b001 1
b00010100 2
b00110 4
b11001 5
b00000000000000000000000000001100 B
1W
#80
0W
#81
b00000000000000000000000000001100 #
b00000000000000000000000000000000 $
0%
1'
0(
1)
1*
b00000000000000000000000000000000 ,
b00000000000000000000000000001100 -
b00000000000001011000010100010011 .
b000 /
b00000000000000000000000000000000 0
b000 1
b00001100 2
b00000 4
b01010 5
1W
#82
0W
#83
b00000000000000000000000000010000 #
b00000000000000000000000000000001 $
b00000000000000000000000000001101 -
b00000000000101011000010110010011 .
b00000000000000000000000000000001 0
b00010000 2
b00001 4
b01011 5
b00000000000000000000000000001100 A
1W
#84
0W
#85
b00000000000000000000000000010100 #
b11111111111111111111111111111000 $
1%
0'
1(
0)
0*
b00000000000000000000000000001101 +
b00000000000000000000000000010001 ,
b11111111111111111111111111111100 -
b11111110011001011001110011100011 .
b001 /
b00000000000000000000000000010001 0
b001 1
b00010100 2
b00110 4
b11001 5
b00000000000000000000000000001101 B
1W
#86
0W
#87
b00000000000000000000000000001100 #
b00000000000000000000000000000000 $
0%
1'
0(
1)
1*
b00000000000000000000000000000000 ,
b00000000000000000000000000001101 -
b00000000000001011000010100010011 .
b000 /
b00000000000000000000000000000000 0
b000 1
b00001100 2
b00000 4
b01010 5
1W
#88
0W
#89
b00000000000000000000000000010000 #
b00000000000000000000000000000001 $
b00000000000000000000000000001110 -
b00000000000101011000010110010011 .
b00000000000000000000000000000001 0
b00010000 2
b00001 4
b01011 5
b00000000000000000000000000001101 A
1W
#90
0W
#91
b00000000000000000000000000010100 #
b11111111111111111111111111111000 $
1%
0'
1(
0)
0*
b00000000000000000000000000001110 +
b00000000000000000000000000010001 ,
b11111111111111111111111111111101 -
b11111110011001011001110011100011 .
b001 /
b00000000000000000000000000010001 0
b001 1
b00010100 2
b00110 4
b11001 5
b00000000000000000000000000001110 B
1W
#92
0W
#93
b00000000000000000000000000001100 #
b00000000000000000000000000000000 $
0%
1'
0(
1)
1*
b00000000000000000000000000000000 ,
b00000000000000000000000000001110 -
b00000000000001011000010100010011 .
b000 /
b00000000000000000000000000000000 0
b000 1
b00001100 2
b00000 4
b01010 5
1W
#94
0W
#95
b00000000000000000000000000010000 #
b00000000000000000000000000000001 $
b00000000000000000000000000001111 -
b00000000000101011000010110010011 .
b00000000000000000000000000000001 0
b00010000 2
b00001 4
b01011 5
b00000000000000000000000000001110 A
1W
#96
0W
#97
b00000000000000000000000000010100 #
b11111111111111111111111111111000 $
1%
0'
1(
0)
0*
b00000000000000000000000000001111 +
b00000000000000000000000000010001 ,
b11111111111111111111111111111110 -
b11111110011001011001110011100011 .
b001 /
b00000000000000000000000000010001 0
b001 1
b00010100 2
b00110 4
b11001 5
b00000000000000000000000000001111 B
1W
#98
0W
#99
b00000000000000000000000000001100 #
b00000000000000000000000000000000 $
0%
1'
0(
1)
1*
b00000000000000000000000000000000 ,
b00000000000000000000000000001111 -
b00000000000001011000010100010011 .
b000 /
b00000000000000000000000000000000 0
b000 1
b00001100 2
b00000 4
b01010 5
1W
#100
0W
#101
b00000000000000000000000000010000 #
b00000000000000000000000000000001 $
b00000000000000000000000000010000 -
b00000000000101011000010110010011 .
b00000000000000000000000000000001 0
b00010000 2
b00001 4
b01011 5
b00000000000000000000000000001111 A
1W
#102
0W
#103
b00000000000000000000000000010100 #
b11111111111111111111111111111000 $
1%
0'
1(
0)
0*
b00000000000000000000000000010000 +
b00000000000000000000000000010001 ,
b11111111111111111111111111111111 -
b11111110011001011001110011100011 .
b001 /
b00000000000000000000000000010001 0
b001 1
b00010100 2
b00110 4
b11001 5
b00000000000000000000000000010000 B
1W
#104
0W
#105
b00000000000000000000000000001100 #
b00000000000000000000000000000000 $
0%
1'
0(
1)
1*
b00000000000000000000000000000000 ,
b00000000000000000000000000010000 -
b00000000000001011000010100010011 .
b000 /
b00000000000000000000000000000000 0
b000 1
b00001100 2
b00000 4
b01010 5
1W
#106
0W
#107
b00000000000000000000000000010000 #
b00000000000000000000000000000001 $
b00000000000000000000000000010001 -
b00000000000101011000010110010011 .
b00000000000000000000000000000001 0
b00010000 2
b00001 4
b01011 5
b00000000000000000000000000010000 A
1W
#108
0W
#109
b00000000000000000000000000010100 #
b11111111111111111111111111111000 $
1&
0'
1(
0)
0*
b00000000000000000000000000010001 +
b00000000000000000000000000010001 ,
b00000000000000000000000000000000 -
b11111110011001011001110011100011 .
b001 /
b00000000000000000000000000010001 0
b001 1
b00010100 2
b00110 4
b11001 5
b00000000000000000000000000010001 B
1W
#110
0W
#111
b00000000000000000000000000011000 #
b11111111111111111111111111110000 $
1%
0&
b00000000000000000000000000000000 ,
b00000000000000000000000000010001 -
b11111110000000110001100011100011 .
b00000000000000000000000000000000 0
b00011000 2
b00110 3
b00000 4
b10001 5
1W
#112
0W
#113
b00000000000000000000000000001000 #
b00000000000000000000000000000000 $
0%
1&
1'
0(
1)
1*
b00000000000000000000000000000000 +
b00000000000000000000000000000000 -
b00000000000000000000010110010011 .
b000 /
b000 1
b00001000 2
b00000 3
b01011 5
1W
#114
0W
#115
b00000000000000000000000000001100 #
b00000000000001011000010100010011 .
b00001100 2
b01011 3
b01010 5
b00000000000000000000000000000000 B
1W
#116
0W
#117
b00000000000000000000000000010000 #
b00000000000000000000000000000001 $
0&
b00000000000000000000000000000001 -
b00000000000101011000010110010011 .
b00000000000000000000000000000001 0
b00010000 2
b00001 4
b01011 5
b00000000000000000000000000000000 A
1W
#118
0W
#119
b00000000000000000000000000010100 #
b11111111111111111111111111111000 $
1%
0'
1(
0)
0*
b00000000000000000000000000000001 +
b00000000000000000000000000010001 ,
b11111111111111111111111111110000 -
b11111110011001011001110011100011 .
b001 /
b00000000000000000000000000010001 0
b001 1
b00010100 2
b00110 4
b11001 5
b00000000000000000000000000000001 B
1W
#120
0W
