data_ram.sv
module data_ram #(
    parameter WIDTH = 32,
              wanted_width = 10
)(
    input logic                clk,
    input logic                Data_WE,
    input logic  [WIDTH -1:0]  Data_addr,
    input logic [WIDTH -1:0]   Data_WD,
    output logic  [WIDTH -1:0] Data_RD

);


logic [wanted_width-1:0] data_mem [2**10-1:0];
logic [wanted_width-1:0] short_addr;

initial begin
        $display("Loading Data_mem.");
        $readmemh("data.mem", data_mem);
end;

always_comb begin
    short_addr = Data_addr[wanted_width-1:0];
    Data_RD = {data_mem[short_addr], data_mem[short_addr+1], data_mem[short_addr+2], data_mem[short_addr+3]};
end

always_ff @(posedge clk)
    if (Data_WE) begin
    data_mem[short_addr] = Data_WD[31:24];
    data_mem[short_addr+1] = Data_WD[23:16];
    data_mem[short_addr+2] = Data_WD[15:8];
    data_mem[short_addr+3] = Data_WD[7:0];
    end

endmodule

ALU_unit.sv
module ALU_unit #(
    parameter WIDTH = 32
)(
    input   logic [WIDTH-1:0] ALUop1,
    input   logic [WIDTH-1:0] RegOp2,
    input   logic [WIDTH-1:0] ImmOp,
    output  logic [WIDTH-1:0] ALUout,
    input   logic [2:0]       ALUctrl,
    input   logic             ALUsrc,
    output  logic             EQ
);

logic [WIDTH-1:0] ALUop2;

always_comb begin
    ALUop2 = ALUsrc ? ImmOp : RegOp2;
    ALUout = ALUctrl[0] ? ALUop1 - ALUop2 : ALUop1 + ALUop2;
    EQ = (ALUop1 == ALUop2);
end

endmodule

signextend.sv
module signextend #(
    parameter Width = 32
)(
    input  logic [Width-1:0] instr,
    input  logic [1:0]       ImmSrc,
    output logic [Width-1:0] ImmOp
);


// assign ImmOp = ImmSrc ? { {20{instr[31]}}, instr[31:20] } : { {20{instr[31]}}, instr[31], instr[7], instr[30:25], instr[11:8], 1'b0 };  

always_comb

    case(ImmSrc)
    2'b00:     ImmOp = { {20{instr[31]}}, instr[31:20] };
    2'b01:     ImmOp = { {20{instr[31]}}, instr[31:25], instr[11:7] };
    2'b10:     ImmOp = { {20{instr[31]}}, instr[31], instr[7], instr[30:25], instr[11:8], 1'b0 };
    default:ImmOp = { {20{instr[31]}}, instr[31:20] };
    endcase

    // Immsrc 00 for lw and addi, 01 for sw, 10 for bne 


endmodule

RegFile.sv
module RegFile #(
    parameter D_WIDTH = 32,
              A_WIDTH = 5
)(
    input logic                clk,
    input logic                WE3,
    input logic                ResultSrc,
    input logic [A_WIDTH-1:0]  AD1,
    input logic [A_WIDTH-1:0]  AD2,
    input logic [A_WIDTH-1:0]  AD3,
    input logic [D_WIDTH-1:0]  ALUout,
    input logic [D_WIDTH-1:0]  Data_RD,
    output logic [D_WIDTH-1:0] RD1,
    output logic [D_WIDTH-1:0] RD2,
    output logic [D_WIDTH-1:0] a0
);

reg [D_WIDTH-1:0] reg_file [31:0];

logic [D_WIDTH-1:0] WD3;

assign WD3 = ResultSrc ? Data_RD : ALUout;

// initial begin
//     // for (i = 0; i < 2**A_WIDTH -1; i++){
//     //     reg_file[i] <= 32'b0
//     // }
//     $display("Loading RegFile.");
//     $readmemh("RegFile.mem", reg_file);
// end;
assign reg_file[0] = 32'b0;

always_ff @( posedge clk ) begin 

    if (WE3) reg_file[AD3] = WD3;
    
end

always_comb begin
    RD1 = reg_file[AD1];
    RD2 = reg_file[AD2];
    a0 <= reg_file[10];
end

endmodule

control_unit.sv
module control_unit #(
    parameter Wid = 32
)(
    input  logic           EQ,
    input  logic [Wid-1:0] instr,
    output logic           RegWrite,
    output logic           ResultSrc,
    output logic           ALUsrc,
    output logic           PCsrc,
    output logic [2:0]     ALUctrl,
    output logic [1:0]     ImmSrc,
    output logic           Data_WE
);

always_comb

    case(instr[6:0])

    7'b0010011:begin //addi
    ALUctrl = instr[14:12];
    RegWrite = 1;
    ImmSrc = 00;
    ALUsrc = 1;
    PCsrc = 0;
    ResultSrc = 0;
    end

    7'b0000011:begin //lw
    ALUctrl = instr[14:12];
    RegWrite = 1;
    ImmSrc = 00;
    ALUsrc = 1;
    PCsrc = 0;
    ResultSrc = 1;
    end

    7'b1100011:begin //bne
    ALUctrl = instr[14:12];
    RegWrite = 0;
    PCsrc = ~EQ;   
    ImmSrc = 10;
    ALUsrc = 0;
    ResultSrc = 0;
    end

    7'b0100011:begin //sw
    ALUctrl = instr[14:12];
    RegWrite = 0;
    ImmSrc = 01;
    ALUsrc = 1;
    PCsrc = 0;
    Data_WE = 1;
    ResultSrc = 1;
    end



    default:begin
    ALUctrl = instr[14:12];
    ImmSrc = 00;
    PCsrc = 0;
    RegWrite = 0;
    ALUsrc = 0;
    ResultSrc = 0;
    Data_WE = 0;
    end

    endcase

    // Immsrc 00 for lw and addi, 01 for sw, 10 for bne 




    // begin                        // add      0110011
    // PCsrc = instr[6];            //addi      0010011
    // ALUsrc = ~instr[6];           //branch    1100011
    // ALUctrl = instr[14:12];      //          ||^ PCsrc
    // RegWrite = ~instr[6];        //          |^   not ALUsrc
    // ImmSrc = instr[6];          //          ^ not RegWrite 
    // end                          //          ALUctrl: funct3

endmodule

instr_rom.sv
module instr_rom 
// #(
//     parameter ADDRESS_WIDTH = 32, //should be in the same length as PC
//               DATA_WIDTH    = 8)
(
    input logic  [31:0]     addr,
    output logic [31:0]     dout

);

logic [7:0] rom_array [2**8-1:0]; //Theoretically, there should be 2^32 in memmory   
logic [7:0] short_addr;                 // but we do not need that many space, so I made to 
                                            // have only 256 memory spaces
//date width should be 8bit because it is a byte addressable memory
//so each instruction consist of four 8-bit byte

initial begin
        $display("Loading Instr_mem.");
        $readmemh("instruction.mem", rom_array);  //read instruction into rom
        // $display(rom_array [0], rom_array [1], rom_array [2],rom_array [3]);
end;

always_comb
    dout <= {rom_array [short_addr[7:0]+3], rom_array [short_addr[7:0]+2], rom_array [short_addr[7:0]+1],rom_array [short_addr[7:0]]};
    // dout <= 8'h11;

endmodule

counter_unit.sv
module counter_unit #(
    parameter PC_WIDTH = 32 // the length of pc and imme
)(
    input  logic clk,
    input  logic rst,
    input  logic PCsrc,
    // input  logic [PC_WIDTH-1:0] PC,
    input  logic [PC_WIDTH-1:0] ImmOp,
    output logic [PC_WIDTH-1:0] PC
);

// logic [PC_WIDTH-1:0] next_PC;
// logic [PC_WIDTH-1:0] branch_PC;

// assign branch_PC = PC + ImmOp;                                        //compute branch_pc
// assign next_PC = PCsrc ? branch_PC : PC + {{PC_WIDTH-1{1'b0}}, 1'b1};    //compute inc_PC

always_ff @ (posedge clk)begin
  if (rst)           PC <= 32'hBFC00000;
  else PC <= PCsrc ? PC + ImmOp : PC + 4;
  // else if (PCsrc)    PC <= PC + ImmOp;
  // else               PC <= PC + 4;
end


endmodule

top.sv
module top #(
    parameter D_WIDTH = 32,
              A_WIDTH = 5
)(
    input  logic        clk,
    input  logic        rst,
    output logic [16:0] a0
);

logic [D_WIDTH-1:0] PC;
logic [D_WIDTH-1:0] ImmOp;
logic               PCsrc;
logic               EQ;
logic               RegWrite;
logic               ALUctrl;
logic               ALUsrc;
logic               ResultSrc;
logic [1:0]         ImmSrc;
logic [A_WIDTH-1:0] AD1;
logic [A_WIDTH-1:0] AD2;
logic [A_WIDTH-1:0] AD3;
logic [D_WIDTH-1:0] RD1;
logic [D_WIDTH-1:0] RD2;
logic [D_WIDTH-1:0] ALUout;
logic [D_WIDTH-1:0] instr;
logic [D_WIDTH-1:0] out;

logic               Data_WE;
logic [D_WIDTH-1:0] Data_addr;
logic [D_WIDTH-1:0] Data_RD;



counter_unit pc_counter(
    .clk(clk),
    .rst(rst),
    .PCsrc(PCsrc),
    .ImmOp(ImmOp),
    .PC(PC)
);

instr_rom instr_mem(
    .addr(PC),
    .dout(instr)
);

control_unit encoder(
    .EQ(EQ),
    .instr(instr),
    .RegWrite(RegWrite),
    .ALUsrc(ALUsrc),
    .PCsrc(PCsrc),
    .ALUctrl(ALUctrl),
    .ImmSrc(ImmSrc),
    .ResultSrc(ResultSrc)
);

RegFile register_file(
    .clk(clk),
    .WE3(RegWrite),
    .AD1(instr[19:15]),
    .AD2(instr[24:20]),
    .AD3(instr[11:7]),
    .RD1(RD1),
    .RD2(RD2),
    .ALUout(ALUout),
    .Data_RD(Data_RD),
    .ResultSrc(ResultSrc),
    .a0(a0)
);

signextend extend(
    .instr(instr),
    .ImmSrc(ImmSrc),
    .ImmOp(ImmOp)
);

ALU_unit ALU(
    .ALUop1(RD1),
    .RegOp2(RD2),
    .ImmOp(ImmOp),
    .ALUctrl(ALUctrl),
    .ALUout(ALUout),
    .ALUsrc(ALUsrc),
    .EQ(EQ)
);

data_ram data_mem(
    .clk(clk),
    .Data_WE(Data_WE),
    .Data_addr(ALUout),
    .Data_RD(Data_RD),
    .Data_WD(RD2)
);



endmodule

top.vcd
$version Generated by VerilatedVcd $end
$date Wed Nov 23 21:41:26 2022 $end
$timescale 1ps $end

 $scope module TOP $end
  $var wire 17 ^ a0 [16:0] $end
  $var wire  1 \ clk $end
  $var wire  1 ] rst $end
  $scope module top $end
   $var wire  5 a AD1 [4:0] $end
   $var wire  5 b AD2 [4:0] $end
   $var wire  5 c AD3 [4:0] $end
   $var wire  1 ( ALUctrl $end
   $var wire 32 . ALUout [31:0] $end
   $var wire  1 ) ALUsrc $end
   $var wire 32 ` A_WIDTH [31:0] $end
   $var wire 32 _ D_WIDTH [31:0] $end
   $var wire 32 1 Data_RD [31:0] $end
   $var wire  1 0 Data_WE $end
   $var wire 32 e Data_addr [31:0] $end
   $var wire  1 & EQ $end
   $var wire 32 $ ImmOp [31:0] $end
   $var wire  2 + ImmSrc [1:0] $end
   $var wire 32 # PC [31:0] $end
   $var wire  1 % PCsrc $end
   $var wire 32 , RD1 [31:0] $end
   $var wire 32 - RD2 [31:0] $end
   $var wire  1 ' RegWrite $end
   $var wire  1 * ResultSrc $end
   $var wire 17 ^ a0 [16:0] $end
   $var wire  1 \ clk $end
   $var wire 32 / instr [31:0] $end
   $var wire 32 d out [31:0] $end
   $var wire  1 ] rst $end
   $scope module ALU $end
    $var wire  3 2 ALUctrl [2:0] $end
    $var wire 32 , ALUop1 [31:0] $end
    $var wire 32 3 ALUop2 [31:0] $end
    $var wire 32 . ALUout [31:0] $end
    $var wire  1 ) ALUsrc $end
    $var wire  1 & EQ $end
    $var wire 32 $ ImmOp [31:0] $end
    $var wire 32 - RegOp2 [31:0] $end
    $var wire 32 _ WIDTH [31:0] $end
   $upscope $end
   $scope module data_mem $end
    $var wire 32 1 Data_RD [31:0] $end
    $var wire 32 - Data_WD [31:0] $end
    $var wire  1 0 Data_WE $end
    $var wire 32 . Data_addr [31:0] $end
    $var wire 32 _ WIDTH [31:0] $end
    $var wire  1 \ clk $end
    $var wire 10 4 short_addr [9:0] $end
    $var wire 32 f wanted_width [31:0] $end
   $upscope $end
   $scope module encoder $end
    $var wire  3 5 ALUctrl [2:0] $end
    $var wire  1 ) ALUsrc $end
    $var wire  1 0 Data_WE $end
    $var wire  1 & EQ $end
    $var wire  2 + ImmSrc [1:0] $end
    $var wire  1 % PCsrc $end
    $var wire  1 ' RegWrite $end
    $var wire  1 * ResultSrc $end
    $var wire 32 _ Wid [31:0] $end
    $var wire 32 / instr [31:0] $end
   $upscope $end
   $scope module extend $end
    $var wire 32 $ ImmOp [31:0] $end
    $var wire  2 + ImmSrc [1:0] $end
    $var wire 32 _ Width [31:0] $end
    $var wire 32 / instr [31:0] $end
   $upscope $end
   $scope module instr_mem $end
    $var wire 32 # addr [31:0] $end
    $var wire 32 / dout [31:0] $end
    $var wire  8 6 short_addr [7:0] $end
   $upscope $end
   $scope module pc_counter $end
    $var wire 32 $ ImmOp [31:0] $end
    $var wire 32 # PC [31:0] $end
    $var wire 32 _ PC_WIDTH [31:0] $end
    $var wire  1 % PCsrc $end
    $var wire  1 \ clk $end
    $var wire  1 ] rst $end
   $upscope $end
   $scope module register_file $end
    $var wire  5 7 AD1 [4:0] $end
    $var wire  5 8 AD2 [4:0] $end
    $var wire  5 9 AD3 [4:0] $end
    $var wire 32 . ALUout [31:0] $end
    $var wire 32 ` A_WIDTH [31:0] $end
    $var wire 32 _ D_WIDTH [31:0] $end
    $var wire 32 1 Data_RD [31:0] $end
    $var wire 32 , RD1 [31:0] $end
    $var wire 32 - RD2 [31:0] $end
    $var wire  1 * ResultSrc $end
    $var wire 32 [ WD3 [31:0] $end
    $var wire  1 ' WE3 $end
    $var wire 32 : a0 [31:0] $end
    $var wire  1 \ clk $end
    $var wire 32 ; reg_file[0] [31:0] $end
    $var wire 32 E reg_file[10] [31:0] $end
    $var wire 32 F reg_file[11] [31:0] $end
    $var wire 32 G reg_file[12] [31:0] $end
    $var wire 32 H reg_file[13] [31:0] $end
    $var wire 32 I reg_file[14] [31:0] $end
    $var wire 32 J reg_file[15] [31:0] $end
    $var wire 32 K reg_file[16] [31:0] $end
    $var wire 32 L reg_file[17] [31:0] $end
    $var wire 32 M reg_file[18] [31:0] $end
    $var wire 32 N reg_file[19] [31:0] $end
    $var wire 32 < reg_file[1] [31:0] $end
    $var wire 32 O reg_file[20] [31:0] $end
    $var wire 32 P reg_file[21] [31:0] $end
    $var wire 32 Q reg_file[22] [31:0] $end
    $var wire 32 R reg_file[23] [31:0] $end
    $var wire 32 S reg_file[24] [31:0] $end
    $var wire 32 T reg_file[25] [31:0] $end
    $var wire 32 U reg_file[26] [31:0] $end
    $var wire 32 V reg_file[27] [31:0] $end
    $var wire 32 W reg_file[28] [31:0] $end
    $var wire 32 X reg_file[29] [31:0] $end
    $var wire 32 = reg_file[2] [31:0] $end
    $var wire 32 Y reg_file[30] [31:0] $end
    $var wire 32 Z reg_file[31] [31:0] $end
    $var wire 32 > reg_file[3] [31:0] $end
    $var wire 32 ? reg_file[4] [31:0] $end
    $var wire 32 @ reg_file[5] [31:0] $end
    $var wire 32 A reg_file[6] [31:0] $end
    $var wire 32 B reg_file[7] [31:0] $end
    $var wire 32 C reg_file[8] [31:0] $end
    $var wire 32 D reg_file[9] [31:0] $end
   $upscope $end
  $upscope $end
 $upscope $end
$enddefinitions $end


#0
b00000000000000000000000000000000 #
b00000000000000000000000000000000 $
0%
0&
0'
0(
0)
0*
b00 +
b00000000000000000000000000000000 ,
b00000000000000000000000000000000 -
b00000000000000000000000000000000 .
b00000000000000000000000000000000 /
00
b00000000000000000000000000000000 1
b000 2
b00000000000000000000000000000000 3
b0000000000 4
b000 5
b00000000 6
b00000 7
b00000 8
b00000 9
b00000000000000000000000000000000 :
b00000000000000000000000000000000 ;
b00000000000000000000000000000000 <
b00000000000000000000000000000000 =
b00000000000000000000000000000000 >
b00000000000000000000000000000000 ?
b00000000000000000000000000000000 @
b00000000000000000000000000000000 A
b00000000000000000000000000000000 B
b00000000000000000000000000000000 C
b00000000000000000000000000000000 D
b00000000000000000000000000000000 E
b00000000000000000000000000000000 F
b00000000000000000000000000000000 G
b00000000000000000000000000000000 H
b00000000000000000000000000000000 I
b00000000000000000000000000000000 J
b00000000000000000000000000000000 K
b00000000000000000000000000000000 L
b00000000000000000000000000000000 M
b00000000000000000000000000000000 N
b00000000000000000000000000000000 O
b00000000000000000000000000000000 P
b00000000000000000000000000000000 Q
b00000000000000000000000000000000 R
b00000000000000000000000000000000 S
b00000000000000000000000000000000 T
b00000000000000000000000000000000 U
b00000000000000000000000000000000 V
b00000000000000000000000000000000 W
b00000000000000000000000000000000 X
b00000000000000000000000000000000 Y
b00000000000000000000000000000000 Z
b00000000000000000000000000000000 [
0\
0]
b00000000000000000 ^
b00000000000000000000000000100000 _
b00000000000000000000000000000101 `
b00000 a
b00000 b
b00000 c
b00000000000000000000000000000000 d
b00000000000000000000000000000000 e
b00000000000000000000000000001010 f
#1
b00000000000000000000010000000000 $
1'
1)
b00000000000000000000010000000000 .
b01000000000000000000001100010011 /
b00000000000000000000000011111110 1
b00000000000000000000010000000000 3
b00110 9
b00000000000000000000010000000000 [
1\
#2
0\
1]
#3
b00000000000000000000010000000000 A
1\
#4
0\
0]
#5
b00000000000000000000000000000100 #
b00000000000000000000000000000000 $
1&
b00000000000000000000000000000000 .
b00000000000000000000010100010011 /
b00000000000000000000000000000000 3
b00000100 6
b01010 9
b00000000000000000000000000000000 [
1\
#6
0\
#7
b00000000000000000000000000001000 #
b00000000000000000000010110010011 /
b00001000 6
b01011 9
1\
#8
0\
#9
b00000000000000000000000000001100 #
b00000000000000000000001110010011 /
b00001100 6
b00111 9
1\
#10
0\
#11
b00000000000000000000000000010000 #
1*
b00000000000001011010010100000011 /
b010 5
b00010000 6
b01011 7
b01010 9
b00000000000000000000000011111110 [
1\
#12
0\
#13
b00000000000000000000000000010100 #
b00000000000000000000000000000100 $
0&
0*
b00000000000000000000000000000100 .
b00000000010001011000010110010011 /
b00000000000000000000000011111101 1
b00000000000000000000000000000100 3
b0000000100 4
b000 5
b00010100 6
b00100 8
b01011 9
b00000000000000000000000011111110 :
b00000000000000000000000011111110 E
b00000000000000000000000000000100 [
1\
b00000000011111110 ^
#14
0\
#15
b00000000000000000000000000011000 #
b11111111111111111111111111111000 $
1%
0'
1(
0)
b10 +
b00000000000000000000000000000100 ,
b00000000000000000000010000000000 -
b11111111111111111111110000000100 .
b11111110011001011001110011100011 /
b001 2
b00000000000000000000010000000000 3
b001 5
b00011000 6
b00110 8
b11001 9
b00000000000000000000000000000100 F
b11111111111111111111110000000100 [
1\
#16
0\
#17
b00000000000000000000000000010000 #
b00000000000000000000000000000000 $
0%
1'
0(
1)
1*
b00 +
b00000000000000000000000000000000 -
b00000000000000000000000000000100 .
b00000000000001011010010100000011 /
b000 2
b00000000000000000000000000000000 3
b010 5
b00010000 6
b00000 8
b01010 9
b00000000000000000000000011111101 [
1\
#18
0\
#19
b00000000000000000000000000010100 #
b00000000000000000000000000000100 $
1&
0*
b00000000000000000000000000001000 .
b00000000010001011000010110010011 /
b00000000000000000000000000000100 3
b0000001000 4
b000 5
b00010100 6
b00100 8
b01011 9
b00000000000000000000000011111101 :
b00000000000000000000000011111101 E
b00000000000000000000000000001000 [
1\
b00000000011111101 ^
#20
0\
#21
b00000000000000000000000000011000 #
b11111111111111111111111111111000 $
1%
0&
0'
1(
0)
b10 +
b00000000000000000000000000001000 ,
b00000000000000000000010000000000 -
b11111111111111111111110000001000 .
b11111110011001011001110011100011 /
b001 2
b00000000000000000000010000000000 3
b001 5
b00011000 6
b00110 8
b11001 9
b00000000000000000000000000001000 F
b11111111111111111111110000001000 [
1\
#22
0\
#23
b00000000000000000000000000010000 #
b00000000000000000000000000000000 $
0%
1'
0(
1)
1*
b00 +
b00000000000000000000000000000000 -
b00000000000000000000000000001000 .
b00000000000001011010010100000011 /
b000 2
b00000000000000000000000000000000 3
b010 5
b00010000 6
b00000 8
b01010 9
b00000000000000000000000011111101 [
1\
#24
0\
#25
b00000000000000000000000000010100 #
b00000000000000000000000000000100 $
0*
b00000000000000000000000000001100 .
b00000000010001011000010110010011 /
b00000000000000000000000000000100 3
b0000001100 4
b000 5
b00010100 6
b00100 8
b01011 9
b00000000000000000000000000001100 [
1\
#26
0\
#27
b00000000000000000000000000011000 #
b11111111111111111111111111111000 $
1%
0'
1(
0)
b10 +
b00000000000000000000000000001100 ,
b00000000000000000000010000000000 -
b11111111111111111111110000001100 .
b11111110011001011001110011100011 /
b001 2
b00000000000000000000010000000000 3
b001 5
b00011000 6
b00110 8
b11001 9
b00000000000000000000000000001100 F
b11111111111111111111110000001100 [
1\
#28
0\
#29
b00000000000000000000000000010000 #
b00000000000000000000000000000000 $
0%
1'
0(
1)
1*
b00 +
b00000000000000000000000000000000 -
b00000000000000000000000000001100 .
b00000000000001011010010100000011 /
b000 2
b00000000000000000000000000000000 3
b010 5
b00010000 6
b00000 8
b01010 9
b00000000000000000000000011111101 [
1\
#30
0\
#31
b00000000000000000000000000010100 #
b00000000000000000000000000000100 $
0*
b00000000000000000000000000010000 .
b00000000010001011000010110010011 /
b00000000000000000000000000000100 3
b0000010000 4
b000 5
b00010100 6
b00100 8
b01011 9
b00000000000000000000000000010000 [
1\
#32
0\
#33
b00000000000000000000000000011000 #
b11111111111111111111111111111000 $
1%
0'
1(
0)
b10 +
b00000000000000000000000000010000 ,
b00000000000000000000010000000000 -
b11111111111111111111110000010000 .
b11111110011001011001110011100011 /
b001 2
b00000000000000000000010000000000 3
b001 5
b00011000 6
b00110 8
b11001 9
b00000000000000000000000000010000 F
b11111111111111111111110000010000 [
1\
#34
0\
#35
b00000000000000000000000000010000 #
b00000000000000000000000000000000 $
0%
1'
0(
1)
1*
b00 +
b00000000000000000000000000000000 -
b00000000000000000000000000010000 .
b00000000000001011010010100000011 /
b000 2
b00000000000000000000000000000000 3
b010 5
b00010000 6
b00000 8
b01010 9
b00000000000000000000000011111101 [
1\
#36
0\
#37
b00000000000000000000000000010100 #
b00000000000000000000000000000100 $
0*
b00000000000000000000000000010100 .
b00000000010001011000010110010011 /
b00000000000000000000000000000100 3
b0000010100 4
b000 5
b00010100 6
b00100 8
b01011 9
b00000000000000000000000000010100 [
1\
#38
0\
#39
b00000000000000000000000000011000 #
b11111111111111111111111111111000 $
1%
0'
1(
0)
b10 +
b00000000000000000000000000010100 ,
b00000000000000000000010000000000 -
b11111111111111111111110000010100 .
b11111110011001011001110011100011 /
b001 2
b00000000000000000000010000000000 3
b001 5
b00011000 6
b00110 8
b11001 9
b00000000000000000000000000010100 F
b11111111111111111111110000010100 [
1\
#40
0\
#41
b00000000000000000000000000010000 #
b00000000000000000000000000000000 $
0%
1'
0(
1)
1*
b00 +
b00000000000000000000000000000000 -
b00000000000000000000000000010100 .
b00000000000001011010010100000011 /
b000 2
b00000000000000000000000000000000 3
b010 5
b00010000 6
b00000 8
b01010 9
b00000000000000000000000011111101 [
1\
#42
0\
#43
b00000000000000000000000000010100 #
b00000000000000000000000000000100 $
0*
b00000000000000000000000000011000 .
b00000000010001011000010110010011 /
b00000000000000000000000011111100 1
b00000000000000000000000000000100 3
b0000011000 4
b000 5
b00010100 6
b00100 8
b01011 9
b00000000000000000000000000011000 [
1\
#44
0\
#45
b00000000000000000000000000011000 #
b11111111111111111111111111111000 $
1%
0'
1(
0)
b10 +
b00000000000000000000000000011000 ,
b00000000000000000000010000000000 -
b11111111111111111111110000011000 .
b11111110011001011001110011100011 /
b001 2
b00000000000000000000010000000000 3
b001 5
b00011000 6
b00110 8
b11001 9
b00000000000000000000000000011000 F
b11111111111111111111110000011000 [
1\
#46
0\
#47
b00000000000000000000000000010000 #
b00000000000000000000000000000000 $
0%
1'
0(
1)
1*
b00 +
b00000000000000000000000000000000 -
b00000000000000000000000000011000 .
b00000000000001011010010100000011 /
b000 2
b00000000000000000000000000000000 3
b010 5
b00010000 6
b00000 8
b01010 9
b00000000000000000000000011111100 [
1\
#48
0\
#49
b00000000000000000000000000010100 #
b00000000000000000000000000000100 $
0*
b00000000000000000000000000011100 .
b00000000010001011000010110010011 /
b00000000000000000000000000000100 3
b0000011100 4
b000 5
b00010100 6
b00100 8
b01011 9
b00000000000000000000000011111100 :
b00000000000000000000000011111100 E
b00000000000000000000000000011100 [
1\
b00000000011111100 ^
#50
0\
#51
b00000000000000000000000000011000 #
b11111111111111111111111111111000 $
1%
0'
1(
0)
b10 +
b00000000000000000000000000011100 ,
b00000000000000000000010000000000 -
b11111111111111111111110000011100 .
b11111110011001011001110011100011 /
b001 2
b00000000000000000000010000000000 3
b001 5
b00011000 6
b00110 8
b11001 9
b00000000000000000000000000011100 F
b11111111111111111111110000011100 [
1\
#52
0\
#53
b00000000000000000000000000010000 #
b00000000000000000000000000000000 $
0%
1'
0(
1)
1*
b00 +
b00000000000000000000000000000000 -
b00000000000000000000000000011100 .
b00000000000001011010010100000011 /
b000 2
b00000000000000000000000000000000 3
b010 5
b00010000 6
b00000 8
b01010 9
b00000000000000000000000011111100 [
1\
#54
0\
#55
b00000000000000000000000000010100 #
b00000000000000000000000000000100 $
0*
b00000000000000000000000000100000 .
b00000000010001011000010110010011 /
b00000000000000000000000011111011 1
b00000000000000000000000000000100 3
b0000100000 4
b000 5
b00010100 6
b00100 8
b01011 9
b00000000000000000000000000100000 [
1\
#56
0\
#57
b00000000000000000000000000011000 #
b11111111111111111111111111111000 $
1%
0'
1(
0)
b10 +
b00000000000000000000000000100000 ,
b00000000000000000000010000000000 -
b11111111111111111111110000100000 .
b11111110011001011001110011100011 /
b001 2
b00000000000000000000010000000000 3
b001 5
b00011000 6
b00110 8
b11001 9
b00000000000000000000000000100000 F
b11111111111111111111110000100000 [
1\
#58
0\
#59
b00000000000000000000000000010000 #
b00000000000000000000000000000000 $
0%
1'
0(
1)
1*
b00 +
b00000000000000000000000000000000 -
b00000000000000000000000000100000 .
b00000000000001011010010100000011 /
b000 2
b00000000000000000000000000000000 3
b010 5
b00010000 6
b00000 8
b01010 9
b00000000000000000000000011111011 [
1\
#60
0\
#61
b00000000000000000000000000010100 #
b00000000000000000000000000000100 $
0*
b00000000000000000000000000100100 .
b00000000010001011000010110010011 /
b00000000000000000000000011111010 1
b00000000000000000000000000000100 3
b0000100100 4
b000 5
b00010100 6
b00100 8
b01011 9
b00000000000000000000000011111011 :
b00000000000000000000000011111011 E
b00000000000000000000000000100100 [
1\
b00000000011111011 ^
#62
0\
#63
b00000000000000000000000000011000 #
b11111111111111111111111111111000 $
1%
0'
1(
0)
b10 +
b00000000000000000000000000100100 ,
b00000000000000000000010000000000 -
b11111111111111111111110000100100 .
b11111110011001011001110011100011 /
b001 2
b00000000000000000000010000000000 3
b001 5
b00011000 6
b00110 8
b11001 9
b00000000000000000000000000100100 F
b11111111111111111111110000100100 [
1\
#64
0\
#65
b00000000000000000000000000010000 #
b00000000000000000000000000000000 $
0%
1'
0(
1)
1*
b00 +
b00000000000000000000000000000000 -
b00000000000000000000000000100100 .
b00000000000001011010010100000011 /
b000 2
b00000000000000000000000000000000 3
b010 5
b00010000 6
b00000 8
b01010 9
b00000000000000000000000011111010 [
1\
#66
0\
#67
b00000000000000000000000000010100 #
b00000000000000000000000000000100 $
0*
b00000000000000000000000000101000 .
b00000000010001011000010110010011 /
b00000000000000000000000000000100 3
b0000101000 4
b000 5
b00010100 6
b00100 8
b01011 9
b00000000000000000000000011111010 :
b00000000000000000000000011111010 E
b00000000000000000000000000101000 [
1\
b00000000011111010 ^
#68
0\
#69
b00000000000000000000000000011000 #
b11111111111111111111111111111000 $
1%
0'
1(
0)
b10 +
b00000000000000000000000000101000 ,
b00000000000000000000010000000000 -
b11111111111111111111110000101000 .
b11111110011001011001110011100011 /
b001 2
b00000000000000000000010000000000 3
b001 5
b00011000 6
b00110 8
b11001 9
b00000000000000000000000000101000 F
b11111111111111111111110000101000 [
1\
#70
0\
#71
b00000000000000000000000000010000 #
b00000000000000000000000000000000 $
0%
1'
0(
1)
1*
b00 +
b00000000000000000000000000000000 -
b00000000000000000000000000101000 .
b00000000000001011010010100000011 /
b000 2
b00000000000000000000000000000000 3
b010 5
b00010000 6
b00000 8
b01010 9
b00000000000000000000000011111010 [
1\
#72
0\
#73
b00000000000000000000000000010100 #
b00000000000000000000000000000100 $
0*
b00000000000000000000000000101100 .
b00000000010001011000010110010011 /
b00000000000000000000000011111001 1
b00000000000000000000000000000100 3
b0000101100 4
b000 5
b00010100 6
b00100 8
b01011 9
b00000000000000000000000000101100 [
1\
#74
0\
#75
b00000000000000000000000000011000 #
b11111111111111111111111111111000 $
1%
0'
1(
0)
b10 +
b00000000000000000000000000101100 ,
b00000000000000000000010000000000 -
b11111111111111111111110000101100 .
b11111110011001011001110011100011 /
b001 2
b00000000000000000000010000000000 3
b001 5
b00011000 6
b00110 8
b11001 9
b00000000000000000000000000101100 F
b11111111111111111111110000101100 [
1\
#76
0\
#77
b00000000000000000000000000010000 #
b00000000000000000000000000000000 $
0%
1'
0(
1)
1*
b00 +
b00000000000000000000000000000000 -
b00000000000000000000000000101100 .
b00000000000001011010010100000011 /
b000 2
b00000000000000000000000000000000 3
b010 5
b00010000 6
b00000 8
b01010 9
b00000000000000000000000011111001 [
1\
#78
0\
#79
b00000000000000000000000000010100 #
b00000000000000000000000000000100 $
0*
b00000000000000000000000000110000 .
b00000000010001011000010110010011 /
b00000000000000000000000011111000 1
b00000000000000000000000000000100 3
b0000110000 4
b000 5
b00010100 6
b00100 8
b01011 9
b00000000000000000000000011111001 :
b00000000000000000000000011111001 E
b00000000000000000000000000110000 [
1\
b00000000011111001 ^
#80
0\
#81
b00000000000000000000000000011000 #
b11111111111111111111111111111000 $
1%
0'
1(
0)
b10 +
b00000000000000000000000000110000 ,
b00000000000000000000010000000000 -
b11111111111111111111110000110000 .
b11111110011001011001110011100011 /
b001 2
b00000000000000000000010000000000 3
b001 5
b00011000 6
b00110 8
b11001 9
b00000000000000000000000000110000 F
b11111111111111111111110000110000 [
1\
#82
0\
#83
b00000000000000000000000000010000 #
b00000000000000000000000000000000 $
0%
1'
0(
1)
1*
b00 +
b00000000000000000000000000000000 -
b00000000000000000000000000110000 .
b00000000000001011010010100000011 /
b000 2
b00000000000000000000000000000000 3
b010 5
b00010000 6
b00000 8
b01010 9
b00000000000000000000000011111000 [
1\
#84
0\
#85
b00000000000000000000000000010100 #
b00000000000000000000000000000100 $
0*
b00000000000000000000000000110100 .
b00000000010001011000010110010011 /
b00000000000000000000000011110111 1
b00000000000000000000000000000100 3
b0000110100 4
b000 5
b00010100 6
b00100 8
b01011 9
b00000000000000000000000011111000 :
b00000000000000000000000011111000 E
b00000000000000000000000000110100 [
1\
b00000000011111000 ^
#86
0\
