data_ram.sv
module data_ram #(
    parameter WIDTH = 32
)(
    input logic                clk,
    input logic                Data_WE,
    input logic  [WIDTH -1:0]  Data_addr,
    input logic [WIDTH -1:0]   Data_WD,
    output logic  [WIDTH -1:0] Data_RD
);


logic [7:0] data_mem [32'hBFC00FFF:32'hBFC00000];

initial begin
        $display("Loading Data_mem.");
        $readmemh("data.mem", data_mem);
end;

always_comb begin
    Data_RD = {data_mem[Data_addr+3], data_mem[Data_addr+2], data_mem[Data_addr+1], data_mem[Data_addr]};
end

always_ff @(posedge clk)
    if (Data_WE) begin
    data_mem[Data_addr+3] = Data_WD[31:24];
    data_mem[Data_addr+2] = Data_WD[23:16];
    data_mem[Data_addr+1] = Data_WD[15:8];
    data_mem[Data_addr] = Data_WD[7:0];
    end

endmodule

ALU_unit.sv
module ALU_unit #(
    parameter WIDTH = 32
)(
    input   logic [WIDTH-1:0] ALUop1,
    input   logic [WIDTH-1:0] RegOp2,
    input   logic [WIDTH-1:0] ImmOp,
    output  logic [WIDTH-1:0] ALUout,
    input   logic [2:0]       ALUctrl,
    input   logic             ALUsrc,
    output  logic             EQ
);

logic [WIDTH-1:0] ALUop2;

always_comb begin
    ALUop2 = ALUsrc ? ImmOp : RegOp2;
    ALUout = ALUctrl[0] ? ALUop1 - ALUop2 : ALUop1 + ALUop2;
    EQ = (ALUop1 == ALUop2);
end

endmodule

signextend.sv
module signextend #(
    parameter Width = 32
)(
    input  logic [Width-1:0] instr,
    input  logic [1:0]       ImmSrc,
    output logic [Width-1:0] ImmOp
);


// assign ImmOp = ImmSrc ? { {20{instr[31]}}, instr[31:20] } : { {20{instr[31]}}, instr[31], instr[7], instr[30:25], instr[11:8], 1'b0 };  

always_comb

    case(ImmSrc)
    2'b00:     ImmOp = { {20{instr[31]}}, instr[31:20] };
    2'b01:     ImmOp = { {20{instr[31]}}, instr[31:25], instr[11:7] };
    2'b10:     ImmOp = { {20{instr[31]}}, instr[31], instr[7], instr[30:25], instr[11:8], 1'b0 };
    default:ImmOp = { {20{instr[31]}}, instr[31:20] };
    endcase

    // Immsrc 00 for lw and addi, 01 for sw, 10 for bne 


endmodule

RegFile.sv
module RegFile #(
    parameter D_WIDTH = 32,
              A_WIDTH = 5
)(
    input logic                clk,
    input logic                WE3,
    input logic                ResultSrc,
    input logic [A_WIDTH-1:0]  AD1,
    input logic [A_WIDTH-1:0]  AD2,
    input logic [A_WIDTH-1:0]  AD3,
    input logic [D_WIDTH-1:0]  ALUout,
    input logic [D_WIDTH-1:0]  Data_RD,
    output logic [D_WIDTH-1:0] RD1,
    output logic [D_WIDTH-1:0] RD2,
    output logic [D_WIDTH-1:0] a0
);

reg [D_WIDTH-1:0] reg_file [31:0];

logic [D_WIDTH-1:0] WD3;

assign WD3 = ResultSrc ? Data_RD : ALUout;

// initial begin
//     // for (i = 0; i < 2**A_WIDTH -1; i++){
//     //     reg_file[i] <= 32'b0
//     // }
//     $display("Loading RegFile.");
//     $readmemh("RegFile.mem", reg_file);
// end;
assign reg_file[0] = 32'b0;

always_ff @( posedge clk ) begin 

    if (WE3) reg_file[AD3] = WD3;
    
end

always_comb begin
    RD1 = reg_file[AD1];
    RD2 = reg_file[AD2];
    a0 <= reg_file[10];
end

endmodule

control_unit.sv
module control_unit #(
    parameter Wid = 32
)(
    input  logic           EQ,
    input  logic [Wid-1:0] instr,
    output logic           RegWrite,
    output logic           ResultSrc,
    output logic           ALUsrc,
    output logic           PCsrc,
    output logic [2:0]     ALUctrl,
    output logic [1:0]     ImmSrc,
    output logic           Data_WE
);

logic [2:0] funct3;
logic [6:0] funct7;
logic [6:0] opcode;
assign funct3 = instr[14:12];
assign opcode = instr[6:0];

always_comb

    case(opcode)

    // 7'b0110011:    //R-type
    //     case(funct3)
    //         3'b000:
    //         3'b001:
    //         3'b010:
    //         3'b011:
    //         3'b100:
    //         3'b101:
    //         3'b110:
    //         3'b111:
    //         default:



    7'b0010011:begin //addi
    ALUctrl = instr[14:12];
    RegWrite = 1;
    ImmSrc = 2'b00;
    ALUsrc = 1;
    PCsrc = 0;
    ResultSrc = 0;
    end

    7'b0000011:begin //lw
    ALUctrl = instr[14:12];
    RegWrite = 1;
    ImmSrc = 2'b00;
    ALUsrc = 1;
    PCsrc = 0;
    ResultSrc = 1;
    end

    7'b1100011:begin //bne
    ALUctrl = instr[14:12];
    RegWrite = 0;
    PCsrc = ~EQ;   
    ImmSrc = 2'b10;
    ALUsrc = 0;
    ResultSrc = 0;
    end

    7'b0100011:begin //sw
    ALUctrl = instr[14:12];
    RegWrite = 0;
    ImmSrc = 2'b01;
    ALUsrc = 1;
    PCsrc = 0;
    Data_WE = 1;
    ResultSrc = 1;
    end



    default:begin
    ALUctrl = instr[14:12];
    ImmSrc = 2'b00;
    PCsrc = 0;
    RegWrite = 0;
    ALUsrc = 0;
    ResultSrc = 0;
    Data_WE = 0;
    end

    endcase

    // Immsrc 00 for lw and addi, 01 for sw, 10 for bne 




    // begin                        // add      0110011
    // PCsrc = instr[6];            //addi      0010011
    // ALUsrc = ~instr[6];           //branch    1100011
    // ALUctrl = instr[14:12];      //          ||^ PCsrc
    // RegWrite = ~instr[6];        //          |^   not ALUsrc
    // ImmSrc = instr[6];          //          ^ not RegWrite 
    // end                          //          ALUctrl: funct3

endmodule

instr_rom.sv
module instr_rom 
// #(
//     parameter ADDRESS_WIDTH = 32, //should be in the same length as PC
//               DATA_WIDTH    = 8)
(
    input logic  [31:0]     addr,
    output logic [31:0]     dout

);

logic [7:0] rom_array [32'h00001FFF:32'h00001000]; //Theoretically, there should be 2^32 in memmory                // but we do not need that many space, so I made to 
                                            // have only 256 memory spaces
//date width should be 8bit because it is a byte addressable memory
//so each instruction consist of four 8-bit byte

initial begin
        $display("Loading Instr_mem.");
        $readmemh("instruction.mem", rom_array);  //read instruction into rom
        // $display(rom_array [0], rom_array [1], rom_array [2],rom_array [3]);
end;

always_comb
    dout <= {rom_array [addr[7:0]], rom_array [addr[7:0]+1], rom_array [addr[7:0]+2],rom_array [addr[7:0]+3]};
    // dout <= 8'h11;

endmodule

counter_unit.sv
module counter_unit #(
    parameter PC_WIDTH = 32 // the length of pc and imme
)(
    input  logic clk,
    input  logic rst,
    input  logic PCsrc,
    // input  logic [PC_WIDTH-1:0] PC,
    input  logic [PC_WIDTH-1:0] ImmOp,
    output logic [PC_WIDTH-1:0] PC
);

// logic [PC_WIDTH-1:0] next_PC;
// logic [PC_WIDTH-1:0] branch_PC;

// assign branch_PC = PC + ImmOp;                                        //compute branch_pc
// assign next_PC = PCsrc ? branch_PC : PC + {{PC_WIDTH-1{1'b0}}, 1'b1};    //compute inc_PC

always_ff @ (posedge clk)begin
  if (rst)           PC <= 32'hBFC00000;
  else PC <= PCsrc ? PC + ImmOp : PC + 4;
  // else if (PCsrc)    PC <= PC + ImmOp;
  // else               PC <= PC + 4;
end


endmodule

top.sv
module top #(
    parameter D_WIDTH = 32,
              A_WIDTH = 5
)(
    input  logic        clk,
    input  logic        rst,
    output logic [16:0] a0
);

logic [D_WIDTH-1:0] PC;
logic [D_WIDTH-1:0] ImmOp;
logic               PCsrc;
logic               EQ;
logic               RegWrite;
logic               ALUctrl;
logic               ALUsrc;
logic               ResultSrc;
logic [1:0]         ImmSrc;
logic [A_WIDTH-1:0] AD1;
logic [A_WIDTH-1:0] AD2;
logic [A_WIDTH-1:0] AD3;
logic [D_WIDTH-1:0] RD1;
logic [D_WIDTH-1:0] RD2;
logic [D_WIDTH-1:0] ALUout;
logic [D_WIDTH-1:0] instr;
logic [D_WIDTH-1:0] out;

logic               Data_WE;
logic [D_WIDTH-1:0] Data_addr;
logic [D_WIDTH-1:0] Data_RD;



counter_unit pc_counter(
    .clk(clk),
    .rst(rst),
    .PCsrc(PCsrc),
    .ImmOp(ImmOp),
    .PC(PC)
);

instr_rom instr_mem(
    .addr(PC),
    .dout(instr)
);

control_unit encoder(
    .EQ(EQ),
    .instr(instr),
    .RegWrite(RegWrite),
    .ALUsrc(ALUsrc),
    .PCsrc(PCsrc),
    .ALUctrl(ALUctrl),
    .ImmSrc(ImmSrc),
    .ResultSrc(ResultSrc)
);

RegFile register_file(
    .clk(clk),
    .WE3(RegWrite),
    .AD1(instr[19:15]),
    .AD2(instr[24:20]),
    .AD3(instr[11:7]),
    .RD1(RD1),
    .RD2(RD2),
    .ALUout(ALUout),
    .Data_RD(Data_RD),
    .ResultSrc(ResultSrc),
    .a0(a0)
);

signextend extend(
    .instr(instr),
    .ImmSrc(ImmSrc),
    .ImmOp(ImmOp)
);

ALU_unit ALU(
    .ALUop1(RD1),
    .RegOp2(RD2),
    .ImmOp(ImmOp),
    .ALUctrl(ALUctrl),
    .ALUout(ALUout),
    .ALUsrc(ALUsrc),
    .EQ(EQ)
);

data_ram data_mem(
    .clk(clk),
    .Data_WE(Data_WE),
    .Data_addr(ALUout),
    .Data_RD(Data_RD),
    .Data_WD(RD2)
);



endmodule

top.vcd
$version Generated by VerilatedVcd $end
$date Wed Nov 30 12:07:05 2022 $end
$timescale 1ps $end

 $scope module TOP $end
  $var wire 17 ^ a0 [16:0] $end
  $var wire  1 \ clk $end
  $var wire  1 ] rst $end
  $scope module top $end
   $var wire  5 a AD1 [4:0] $end
   $var wire  5 b AD2 [4:0] $end
   $var wire  5 c AD3 [4:0] $end
   $var wire  1 ( ALUctrl $end
   $var wire 32 . ALUout [31:0] $end
   $var wire  1 ) ALUsrc $end
   $var wire 32 ` A_WIDTH [31:0] $end
   $var wire 32 _ D_WIDTH [31:0] $end
   $var wire 32 1 Data_RD [31:0] $end
   $var wire  1 0 Data_WE $end
   $var wire 32 e Data_addr [31:0] $end
   $var wire  1 & EQ $end
   $var wire 32 $ ImmOp [31:0] $end
   $var wire  2 + ImmSrc [1:0] $end
   $var wire 32 # PC [31:0] $end
   $var wire  1 % PCsrc $end
   $var wire 32 , RD1 [31:0] $end
   $var wire 32 - RD2 [31:0] $end
   $var wire  1 ' RegWrite $end
   $var wire  1 * ResultSrc $end
   $var wire 17 ^ a0 [16:0] $end
   $var wire  1 \ clk $end
   $var wire 32 / instr [31:0] $end
   $var wire 32 d out [31:0] $end
   $var wire  1 ] rst $end
   $scope module ALU $end
    $var wire  3 2 ALUctrl [2:0] $end
    $var wire 32 , ALUop1 [31:0] $end
    $var wire 32 3 ALUop2 [31:0] $end
    $var wire 32 . ALUout [31:0] $end
    $var wire  1 ) ALUsrc $end
    $var wire  1 & EQ $end
    $var wire 32 $ ImmOp [31:0] $end
    $var wire 32 - RegOp2 [31:0] $end
    $var wire 32 _ WIDTH [31:0] $end
   $upscope $end
   $scope module data_mem $end
    $var wire 32 1 Data_RD [31:0] $end
    $var wire 32 - Data_WD [31:0] $end
    $var wire  1 0 Data_WE $end
    $var wire 32 . Data_addr [31:0] $end
    $var wire 32 _ WIDTH [31:0] $end
    $var wire  1 \ clk $end
   $upscope $end
   $scope module encoder $end
    $var wire  3 4 ALUctrl [2:0] $end
    $var wire  1 ) ALUsrc $end
    $var wire  1 0 Data_WE $end
    $var wire  1 & EQ $end
    $var wire  2 + ImmSrc [1:0] $end
    $var wire  1 % PCsrc $end
    $var wire  1 ' RegWrite $end
    $var wire  1 * ResultSrc $end
    $var wire 32 _ Wid [31:0] $end
    $var wire  3 5 funct3 [2:0] $end
    $var wire  7 f funct7 [6:0] $end
    $var wire 32 / instr [31:0] $end
    $var wire  7 6 opcode [6:0] $end
   $upscope $end
   $scope module extend $end
    $var wire 32 $ ImmOp [31:0] $end
    $var wire  2 + ImmSrc [1:0] $end
    $var wire 32 _ Width [31:0] $end
    $var wire 32 / instr [31:0] $end
   $upscope $end
   $scope module instr_mem $end
    $var wire 32 # addr [31:0] $end
    $var wire 32 / dout [31:0] $end
   $upscope $end
   $scope module pc_counter $end
    $var wire 32 $ ImmOp [31:0] $end
    $var wire 32 # PC [31:0] $end
    $var wire 32 _ PC_WIDTH [31:0] $end
    $var wire  1 % PCsrc $end
    $var wire  1 \ clk $end
    $var wire  1 ] rst $end
   $upscope $end
   $scope module register_file $end
    $var wire  5 7 AD1 [4:0] $end
    $var wire  5 8 AD2 [4:0] $end
    $var wire  5 9 AD3 [4:0] $end
    $var wire 32 . ALUout [31:0] $end
    $var wire 32 ` A_WIDTH [31:0] $end
    $var wire 32 _ D_WIDTH [31:0] $end
    $var wire 32 1 Data_RD [31:0] $end
    $var wire 32 , RD1 [31:0] $end
    $var wire 32 - RD2 [31:0] $end
    $var wire  1 * ResultSrc $end
    $var wire 32 [ WD3 [31:0] $end
    $var wire  1 ' WE3 $end
    $var wire 32 : a0 [31:0] $end
    $var wire  1 \ clk $end
    $var wire 32 ; reg_file[0] [31:0] $end
    $var wire 32 E reg_file[10] [31:0] $end
    $var wire 32 F reg_file[11] [31:0] $end
    $var wire 32 G reg_file[12] [31:0] $end
    $var wire 32 H reg_file[13] [31:0] $end
    $var wire 32 I reg_file[14] [31:0] $end
    $var wire 32 J reg_file[15] [31:0] $end
    $var wire 32 K reg_file[16] [31:0] $end
    $var wire 32 L reg_file[17] [31:0] $end
    $var wire 32 M reg_file[18] [31:0] $end
    $var wire 32 N reg_file[19] [31:0] $end
    $var wire 32 < reg_file[1] [31:0] $end
    $var wire 32 O reg_file[20] [31:0] $end
    $var wire 32 P reg_file[21] [31:0] $end
    $var wire 32 Q reg_file[22] [31:0] $end
    $var wire 32 R reg_file[23] [31:0] $end
    $var wire 32 S reg_file[24] [31:0] $end
    $var wire 32 T reg_file[25] [31:0] $end
    $var wire 32 U reg_file[26] [31:0] $end
    $var wire 32 V reg_file[27] [31:0] $end
    $var wire 32 W reg_file[28] [31:0] $end
    $var wire 32 X reg_file[29] [31:0] $end
    $var wire 32 = reg_file[2] [31:0] $end
    $var wire 32 Y reg_file[30] [31:0] $end
    $var wire 32 Z reg_file[31] [31:0] $end
    $var wire 32 > reg_file[3] [31:0] $end
    $var wire 32 ? reg_file[4] [31:0] $end
    $var wire 32 @ reg_file[5] [31:0] $end
    $var wire 32 A reg_file[6] [31:0] $end
    $var wire 32 B reg_file[7] [31:0] $end
    $var wire 32 C reg_file[8] [31:0] $end
    $var wire 32 D reg_file[9] [31:0] $end
   $upscope $end
  $upscope $end
 $upscope $end
$enddefinitions $end


#0
b00000000000000000000000000000000 #
b00000000000000000000000000000000 $
0%
0&
0'
0(
0)
0*
b00 +
b00000000000000000000000000000000 ,
b00000000000000000000000000000000 -
b00000000000000000000000000000000 .
b00000000000000000000000000000000 /
00
b00000000000000000000000000000000 1
b000 2
b00000000000000000000000000000000 3
b000 4
b000 5
b0000000 6
b00000 7
b00000 8
b00000 9
b00000000000000000000000000000000 :
b00000000000000000000000000000000 ;
b00000000000000000000000000000000 <
b00000000000000000000000000000000 =
b00000000000000000000000000000000 >
b00000000000000000000000000000000 ?
b00000000000000000000000000000000 @
b00000000000000000000000000000000 A
b00000000000000000000000000000000 B
b00000000000000000000000000000000 C
b00000000000000000000000000000000 D
b00000000000000000000000000000000 E
b00000000000000000000000000000000 F
b00000000000000000000000000000000 G
b00000000000000000000000000000000 H
b00000000000000000000000000000000 I
b00000000000000000000000000000000 J
b00000000000000000000000000000000 K
b00000000000000000000000000000000 L
b00000000000000000000000000000000 M
b00000000000000000000000000000000 N
b00000000000000000000000000000000 O
b00000000000000000000000000000000 P
b00000000000000000000000000000000 Q
b00000000000000000000000000000000 R
b00000000000000000000000000000000 S
b00000000000000000000000000000000 T
b00000000000000000000000000000000 U
b00000000000000000000000000000000 V
b00000000000000000000000000000000 W
b00000000000000000000000000000000 X
b00000000000000000000000000000000 Y
b00000000000000000000000000000000 Z
b00000000000000000000000000000000 [
0\
0]
b00000000000000000 ^
b00000000000000000000000000100000 _
b00000000000000000000000000000101 `
b00000 a
b00000 b
b00000 c
b00000000000000000000000000000000 d
b00000000000000000000000000000000 e
b0000000 f
#1
1&
b11111110000000000000000000000000 1
1\
#2
0\
1]
#3
1\
#4
0\
0]
#5
b00000000000000000000000000000100 #
1\
#6
0\
#7
b00000000000000000000000000001000 #
1\
#8
0\
#9
b00000000000000000000000000001100 #
1\
#10
0\
#11
b00000000000000000000000000010000 #
1\
#12
0\
#13
b00000000000000000000000000010100 #
1\
#14
0\
#15
b00000000000000000000000000011000 #
1\
#16
0\
#17
b00000000000000000000000000011100 #
1\
#18
0\
#19
b00000000000000000000000000100000 #
1\
#20
0\
#21
b00000000000000000000000000100100 #
1\
#22
0\
#23
b00000000000000000000000000101000 #
1\
#24
0\
#25
b00000000000000000000000000101100 #
1\
#26
0\
#27
b00000000000000000000000000110000 #
1\
#28
0\
#29
b00000000000000000000000000110100 #
1\
#30
0\
#31
b00000000000000000000000000111000 #
1\
#32
0\
#33
b00000000000000000000000000111100 #
1\
#34
0\
#35
b00000000000000000000000001000000 #
1\
#36
0\
#37
b00000000000000000000000001000100 #
1\
#38
0\
#39
b00000000000000000000000001001000 #
1\
#40
0\
#41
b00000000000000000000000001001100 #
1\
#42
0\
#43
b00000000000000000000000001010000 #
1\
#44
0\
#45
b00000000000000000000000001010100 #
1\
#46
0\
#47
b00000000000000000000000001011000 #
1\
#48
0\
#49
b00000000000000000000000001011100 #
1\
#50
0\
#51
b00000000000000000000000001100000 #
1\
#52
0\
#53
b00000000000000000000000001100100 #
1\
#54
0\
#55
b00000000000000000000000001101000 #
1\
#56
0\
#57
b00000000000000000000000001101100 #
1\
#58
0\
#59
b00000000000000000000000001110000 #
1\
#60
0\
#61
b00000000000000000000000001110100 #
1\
#62
0\
#63
b00000000000000000000000001111000 #
1\
#64
0\
#65
b00000000000000000000000001111100 #
1\
#66
0\
#67
b00000000000000000000000010000000 #
1\
#68
0\
#69
b00000000000000000000000010000100 #
1\
#70
0\
#71
b00000000000000000000000010001000 #
1\
#72
0\
#73
b00000000000000000000000010001100 #
1\
#74
0\
#75
b00000000000000000000000010010000 #
1\
#76
0\
#77
b00000000000000000000000010010100 #
1\
#78
0\
#79
b00000000000000000000000010011000 #
1\
#80
0\
#81
b00000000000000000000000010011100 #
1\
#82
0\
#83
b00000000000000000000000010100000 #
1\
#84
0\
#85
b00000000000000000000000010100100 #
1\
#86
0\
#87
b00000000000000000000000010101000 #
1\
#88
0\
#89
b00000000000000000000000010101100 #
1\
#90
0\
#91
b00000000000000000000000010110000 #
1\
#92
0\
#93
b00000000000000000000000010110100 #
1\
#94
0\
#95
b00000000000000000000000010111000 #
1\
#96
0\
#97
b00000000000000000000000010111100 #
1\
#98
0\
#99
b00000000000000000000000011000000 #
1\
#100
0\
#101
b00000000000000000000000011000100 #
1\
#102
0\
#103
b00000000000000000000000011001000 #
1\
#104
0\
#105
b00000000000000000000000011001100 #
1\
#106
0\
#107
b00000000000000000000000011010000 #
1\
#108
0\
#109
b00000000000000000000000011010100 #
1\
#110
0\
#111
b00000000000000000000000011011000 #
1\
#112
0\
#113
b00000000000000000000000011011100 #
1\
#114
0\
#115
b00000000000000000000000011100000 #
1\
#116
0\
#117
b00000000000000000000000011100100 #
1\
#118
0\
#119
b00000000000000000000000011101000 #
1\
#120
0\
#121
b00000000000000000000000011101100 #
1\
#122
0\
#123
b00000000000000000000000011110000 #
1\
#124
0\
#125
b00000000000000000000000011110100 #
1\
#126
0\
#127
b00000000000000000000000011111000 #
1\
#128
0\
#129
b00000000000000000000000011111100 #
1\
#130
0\
#131
b00000000000000000000000100000000 #
1\
#132
0\
#133
b00000000000000000000000100000100 #
1\
#134
0\
#135
b00000000000000000000000100001000 #
1\
#136
0\
#137
b00000000000000000000000100001100 #
1\
#138
0\
#139
b00000000000000000000000100010000 #
1\
#140
0\
#141
b00000000000000000000000100010100 #
1\
#142
0\
#143
b00000000000000000000000100011000 #
1\
#144
0\
#145
b00000000000000000000000100011100 #
1\
#146
0\
#147
b00000000000000000000000100100000 #
1\
#148
0\
#149
b00000000000000000000000100100100 #
1\
#150
0\
#151
b00000000000000000000000100101000 #
1\
#152
0\
#153
b00000000000000000000000100101100 #
1\
#154
0\
#155
b00000000000000000000000100110000 #
1\
#156
0\
#157
b00000000000000000000000100110100 #
1\
#158
0\
#159
b00000000000000000000000100111000 #
1\
#160
0\
#161
b00000000000000000000000100111100 #
1\
#162
0\
#163
b00000000000000000000000101000000 #
1\
#164
0\
#165
b00000000000000000000000101000100 #
1\
#166
0\
#167
b00000000000000000000000101001000 #
1\
#168
0\
#169
b00000000000000000000000101001100 #
1\
#170
0\
#171
b00000000000000000000000101010000 #
1\
#172
0\
#173
b00000000000000000000000101010100 #
1\
#174
0\
#175
b00000000000000000000000101011000 #
1\
#176
0\
#177
b00000000000000000000000101011100 #
1\
#178
0\
#179
b00000000000000000000000101100000 #
1\
#180
0\
#181
b00000000000000000000000101100100 #
1\
#182
0\
#183
b00000000000000000000000101101000 #
1\
#184
0\
#185
b00000000000000000000000101101100 #
1\
#186
0\
#187
b00000000000000000000000101110000 #
1\
#188
0\
#189
b00000000000000000000000101110100 #
1\
#190
0\
#191
b00000000000000000000000101111000 #
1\
#192
0\
#193
b00000000000000000000000101111100 #
1\
#194
0\
#195
b00000000000000000000000110000000 #
1\
#196
0\
#197
b00000000000000000000000110000100 #
1\
#198
0\
#199
b00000000000000000000000110001000 #
1\
#200
0\
#201
b00000000000000000000000110001100 #
1\
#202
0\
#203
b00000000000000000000000110010000 #
1\
#204
0\
#205
b00000000000000000000000110010100 #
1\
#206
0\
#207
b00000000000000000000000110011000 #
1\
#208
0\
#209
b00000000000000000000000110011100 #
1\
#210
0\
#211
b00000000000000000000000110100000 #
1\
#212
0\
#213
b00000000000000000000000110100100 #
1\
#214
0\
#215
b00000000000000000000000110101000 #
1\
#216
0\
#217
b00000000000000000000000110101100 #
1\
#218
0\
#219
b00000000000000000000000110110000 #
1\
#220
0\
#221
b00000000000000000000000110110100 #
1\
#222
0\
#223
b00000000000000000000000110111000 #
1\
#224
0\
#225
b00000000000000000000000110111100 #
1\
#226
0\
#227
b00000000000000000000000111000000 #
1\
#228
0\
#229
b00000000000000000000000111000100 #
1\
#230
0\
#231
b00000000000000000000000111001000 #
1\
#232
0\
#233
b00000000000000000000000111001100 #
1\
#234
0\
#235
b00000000000000000000000111010000 #
1\
#236
0\
#237
b00000000000000000000000111010100 #
1\
#238
0\
#239
b00000000000000000000000111011000 #
1\
#240
0\
#241
b00000000000000000000000111011100 #
1\
#242
0\
#243
b00000000000000000000000111100000 #
1\
#244
0\
#245
b00000000000000000000000111100100 #
1\
#246
0\
#247
b00000000000000000000000111101000 #
1\
#248
0\
#249
b00000000000000000000000111101100 #
1\
#250
0\
#251
b00000000000000000000000111110000 #
1\
#252
0\
#253
b00000000000000000000000111110100 #
1\
#254
0\
#255
b00000000000000000000000111111000 #
1\
#256
0\
#257
b00000000000000000000000111111100 #
1\
#258
0\
#259
b00000000000000000000001000000000 #
1\
#260
0\
#261
b00000000000000000000001000000100 #
1\
#262
0\
#263
b00000000000000000000001000001000 #
1\
#264
0\
#265
b00000000000000000000001000001100 #
1\
#266
0\
#267
b00000000000000000000001000010000 #
1\
#268
0\
#269
b00000000000000000000001000010100 #
1\
#270
0\
#271
b00000000000000000000001000011000 #
1\
#272
0\
#273
b00000000000000000000001000011100 #
1\
#274
0\
#275
b00000000000000000000001000100000 #
1\
#276
0\
#277
b00000000000000000000001000100100 #
1\
#278
0\
#279
b00000000000000000000001000101000 #
1\
#280
0\
#281
b00000000000000000000001000101100 #
1\
#282
0\
#283
b00000000000000000000001000110000 #
1\
#284
0\
#285
b00000000000000000000001000110100 #
1\
#286
0\
#287
b00000000000000000000001000111000 #
1\
#288
0\
#289
b00000000000000000000001000111100 #
1\
#290
0\
#291
b00000000000000000000001001000000 #
1\
#292
0\
#293
b00000000000000000000001001000100 #
1\
#294
0\
#295
b00000000000000000000001001001000 #
1\
#296
0\
#297
b00000000000000000000001001001100 #
1\
#298
0\
#299
b00000000000000000000001001010000 #
1\
#300
0\
#301
b00000000000000000000001001010100 #
1\
#302
0\
#303
b00000000000000000000001001011000 #
1\
#304
0\
#305
b00000000000000000000001001011100 #
1\
#306
0\
#307
b00000000000000000000001001100000 #
1\
#308
0\
#309
b00000000000000000000001001100100 #
1\
#310
0\
#311
b00000000000000000000001001101000 #
1\
#312
0\
#313
b00000000000000000000001001101100 #
1\
#314
0\
#315
b00000000000000000000001001110000 #
1\
#316
0\
#317
b00000000000000000000001001110100 #
1\
#318
0\
#319
b00000000000000000000001001111000 #
1\
#320
0\
#321
b00000000000000000000001001111100 #
1\
#322
0\
#323
b00000000000000000000001010000000 #
1\
#324
0\
#325
b00000000000000000000001010000100 #
1\
#326
0\
#327
b00000000000000000000001010001000 #
1\
#328
0\
#329
b00000000000000000000001010001100 #
1\
#330
0\
#331
b00000000000000000000001010010000 #
1\
#332
0\
#333
b00000000000000000000001010010100 #
1\
#334
0\
#335
b00000000000000000000001010011000 #
1\
#336
0\
#337
b00000000000000000000001010011100 #
1\
#338
0\
#339
b00000000000000000000001010100000 #
1\
#340
0\
#341
b00000000000000000000001010100100 #
1\
#342
0\
#343
b00000000000000000000001010101000 #
1\
#344
0\
#345
b00000000000000000000001010101100 #
1\
#346
0\
#347
b00000000000000000000001010110000 #
1\
#348
0\
#349
b00000000000000000000001010110100 #
1\
#350
0\
#351
b00000000000000000000001010111000 #
1\
#352
0\
#353
b00000000000000000000001010111100 #
1\
#354
0\
#355
b00000000000000000000001011000000 #
1\
#356
0\
#357
b00000000000000000000001011000100 #
1\
#358
0\
#359
b00000000000000000000001011001000 #
1\
#360
0\
#361
b00000000000000000000001011001100 #
1\
#362
0\
#363
b00000000000000000000001011010000 #
1\
#364
0\
#365
b00000000000000000000001011010100 #
1\
#366
0\
#367
b00000000000000000000001011011000 #
1\
#368
0\
#369
b00000000000000000000001011011100 #
1\
#370
0\
#371
b00000000000000000000001011100000 #
1\
#372
0\
#373
b00000000000000000000001011100100 #
1\
#374
0\
#375
b00000000000000000000001011101000 #
1\
#376
0\
#377
b00000000000000000000001011101100 #
1\
#378
0\
#379
b00000000000000000000001011110000 #
1\
#380
0\
#381
b00000000000000000000001011110100 #
1\
#382
0\
#383
b00000000000000000000001011111000 #
1\
#384
0\
#385
b00000000000000000000001011111100 #
1\
#386
0\
#387
b00000000000000000000001100000000 #
1\
#388
0\
#389
b00000000000000000000001100000100 #
1\
#390
0\
#391
b00000000000000000000001100001000 #
1\
#392
0\
#393
b00000000000000000000001100001100 #
1\
#394
0\
#395
b00000000000000000000001100010000 #
1\
#396
0\
#397
b00000000000000000000001100010100 #
1\
#398
0\
#399
b00000000000000000000001100011000 #
1\
#400
0\
#401
b00000000000000000000001100011100 #
1\
#402
0\
#403
b00000000000000000000001100100000 #
1\
#404
0\
#405
b00000000000000000000001100100100 #
1\
#406
0\
#407
b00000000000000000000001100101000 #
1\
#408
0\
#409
b00000000000000000000001100101100 #
1\
#410
0\
#411
b00000000000000000000001100110000 #
1\
#412
0\
#413
b00000000000000000000001100110100 #
1\
#414
0\
#415
b00000000000000000000001100111000 #
1\
#416
0\
#417
b00000000000000000000001100111100 #
1\
#418
0\
#419
b00000000000000000000001101000000 #
1\
#420
0\
#421
b00000000000000000000001101000100 #
1\
#422
0\
#423
b00000000000000000000001101001000 #
1\
#424
0\
#425
b00000000000000000000001101001100 #
1\
#426
0\
#427
b00000000000000000000001101010000 #
1\
#428
0\
#429
b00000000000000000000001101010100 #
1\
#430
0\
#431
b00000000000000000000001101011000 #
1\
#432
0\
#433
b00000000000000000000001101011100 #
1\
#434
0\
#435
b00000000000000000000001101100000 #
1\
#436
0\
#437
b00000000000000000000001101100100 #
1\
#438
0\
#439
b00000000000000000000001101101000 #
1\
#440
0\
#441
b00000000000000000000001101101100 #
1\
#442
0\
#443
b00000000000000000000001101110000 #
1\
#444
0\
#445
b00000000000000000000001101110100 #
1\
#446
0\
#447
b00000000000000000000001101111000 #
1\
#448
0\
#449
b00000000000000000000001101111100 #
1\
#450
0\
#451
b00000000000000000000001110000000 #
1\
#452
0\
#453
b00000000000000000000001110000100 #
1\
#454
0\
#455
b00000000000000000000001110001000 #
1\
#456
0\
#457
b00000000000000000000001110001100 #
1\
#458
0\
#459
b00000000000000000000001110010000 #
1\
#460
0\
#461
b00000000000000000000001110010100 #
1\
#462
0\
#463
b00000000000000000000001110011000 #
1\
#464
0\
#465
b00000000000000000000001110011100 #
1\
#466
0\
#467
b00000000000000000000001110100000 #
1\
#468
0\
#469
b00000000000000000000001110100100 #
1\
#470
0\
#471
b00000000000000000000001110101000 #
1\
#472
0\
#473
b00000000000000000000001110101100 #
1\
#474
0\
#475
b00000000000000000000001110110000 #
1\
#476
0\
#477
b00000000000000000000001110110100 #
1\
#478
0\
#479
b00000000000000000000001110111000 #
1\
#480
0\
#481
b00000000000000000000001110111100 #
1\
#482
0\
#483
b00000000000000000000001111000000 #
1\
#484
0\
#485
b00000000000000000000001111000100 #
1\
#486
0\
#487
b00000000000000000000001111001000 #
1\
#488
0\
#489
b00000000000000000000001111001100 #
1\
#490
0\
#491
b00000000000000000000001111010000 #
1\
#492
0\
#493
b00000000000000000000001111010100 #
1\
#494
0\
#495
b00000000000000000000001111011000 #
1\
#496
0\
#497
b00000000000000000000001111011100 #
1\
#498
0\
#499
b00000000000000000000001111100000 #
1\
#500
0\
#501
b00000000000000000000001111100100 #
1\
#502
0\
#503
b00000000000000000000001111101000 #
1\
#504
0\
#505
b00000000000000000000001111101100 #
1\
#506
0\
#507
b00000000000000000000001111110000 #
1\
#508
0\
#509
b00000000000000000000001111110100 #
1\
#510
0\
#511
b00000000000000000000001111111000 #
1\
#512
0\
#513
b00000000000000000000001111111100 #
1\
#514
0\
#515
b00000000000000000000010000000000 #
1\
#516
0\
#517
b00000000000000000000010000000100 #
1\
#518
0\
#519
b00000000000000000000010000001000 #
1\
