data_ram.sv
module data_ram #(
    parameter WIDTH = 32
)(
    input logic                clk,
    input logic                Data_WE,
    input logic  [WIDTH -1:0]  Data_addr,
    input logic [WIDTH -1:0]   Data_WD,
    output logic  [WIDTH -1:0] Data_RD

);


logic [7:0] data_mem [2**8-1:0];
logic [7:0] short_addr;

initial begin
        $display("Loading Data_mem.");
        $readmemh("data.mem", data_mem);
end;

always_comb begin
    short_addr = Data_addr[7:0];
    Data_RD = {data_mem[short_addr], data_mem[short_addr+1], data_mem[short_addr+2], data_mem[short_addr+3]};
end

always_ff @(posedge clk)
    if (Data_WE) begin
    data_mem[short_addr] = Data_WD[31:24];
    data_mem[short_addr+1] = Data_WD[23:16];
    data_mem[short_addr+2] = Data_WD[15:8];
    data_mem[short_addr+3] = Data_WD[7:0];
    end

endmodule

ALU_unit.sv
module ALU_unit #(
    parameter WIDTH = 32
)(
    input   logic [WIDTH-1:0] ALUop1,
    input   logic [WIDTH-1:0] RegOp2,
    input   logic [WIDTH-1:0] ImmOp,
    output  logic [WIDTH-1:0] ALUout,
    input   logic [2:0]       ALUctrl,
    input   logic             ALUsrc,
    output  logic             EQ
);

logic [WIDTH-1:0] ALUop2;

always_comb begin
    ALUop2 = ALUsrc ? ImmOp : RegOp2;
    ALUout = ALUctrl[0] ? ALUop1 - ALUop2 : ALUop1 + ALUop2;
    EQ = (ALUop1 == ALUop2);
end

endmodule

signextend.sv
module signextend #(
    parameter Width = 32
)(
    input  logic [Width-1:0] instr,
    input  logic [1:0]       ImmSrc,
    output logic [Width-1:0] ImmOp
);


// assign ImmOp = ImmSrc ? { {20{instr[31]}}, instr[31:20] } : { {20{instr[31]}}, instr[31], instr[7], instr[30:25], instr[11:8], 1'b0 };  

always_comb

    case(ImmSrc)
    2'b00:     ImmOp = { {20{instr[31]}}, instr[31:20] };
    2'b01:     ImmOp = { {20{instr[31]}}, instr[31:25], instr[11:7] };
    2'b10:     ImmOp = { {20{instr[31]}}, instr[31], instr[7], instr[30:25], instr[11:8], 1'b0 };
    default:ImmOp = { {20{instr[31]}}, instr[31:20] };
    endcase

    // Immsrc 00 for lw and addi, 01 for sw, 10 for bne 


endmodule

RegFile.sv
module RegFile #(
    parameter D_WIDTH = 32,
              A_WIDTH = 5
)(
    input logic                clk,
    input logic                WE3,
    input logic                ResultSrc,
    input logic [A_WIDTH-1:0]  AD1,
    input logic [A_WIDTH-1:0]  AD2,
    input logic [A_WIDTH-1:0]  AD3,
    input logic [D_WIDTH-1:0]  ALUout,
    input logic [D_WIDTH-1:0]  Data_RD,
    output logic [D_WIDTH-1:0] RD1,
    output logic [D_WIDTH-1:0] RD2,
    output logic [D_WIDTH-1:0] a0
);

reg [D_WIDTH-1:0] reg_file [31:0];

logic [D_WIDTH-1:0] WD3;

assign WD3 = ResultSrc ? Data_RD : ALUout;

// initial begin
//     // for (i = 0; i < 2**A_WIDTH -1; i++){
//     //     reg_file[i] <= 32'b0
//     // }
//     $display("Loading RegFile.");
//     $readmemh("RegFile.mem", reg_file);
// end;
assign reg_file[0] = 32'b0;

always_ff @( posedge clk ) begin 

    if (WE3) reg_file[AD3] = WD3;
    
end

always_comb begin
    RD1 = reg_file[AD1];
    RD2 = reg_file[AD2];
    a0 <= reg_file[10];
end

endmodule

control_unit.sv
module control_unit #(
    parameter Wid = 32
)(
    input  logic           EQ,
    input  logic [Wid-1:0] instr,
    output logic           RegWrite,
    output logic           ResultSrc,
    output logic           ALUsrc,
    output logic           PCsrc,
    output logic [2:0]     ALUctrl,
    output logic [1:0]     ImmSrc
);

always_comb

    case(instr[6:0])

    7'b0010011:begin //addi
    ALUctrl = instr[14:12];
    RegWrite = 1;
    ImmSrc = 00;
    ALUsrc = 1;
    PCsrc = 0;
    ResultSrc = 0;
    end

    7'b0000011:begin //lw
    ALUctrl = instr[14:12];
    RegWrite = 1;
    ImmSrc = 00;
    ALUsrc = 1;
    PCsrc = 0;
    ResultSrc = 1;
    end

    7'b1100011:begin //bne
    ALUctrl = instr[14:12];
    RegWrite = 0;
    PCsrc = ~EQ;   
    ImmSrc = 10;
    ALUsrc = 0;
    end

    7'b0100011:begin //sw
    ALUctrl = instr[14:12];
    RegWrite = 1;
    ImmSrc = 01;
    ALUsrc = 1;
    PCsrc = 0;
    end



    default:begin
    ALUctrl = instr[14:12];
    ImmSrc = 00;
    PCsrc = 0;
    RegWrite = 0;
    ALUsrc = 0;
    ResultSrc = 0;
    end

    endcase

    // Immsrc 00 for lw and addi, 01 for sw, 10 for bne 




    // begin                        // add      0110011
    // PCsrc = instr[6];            //addi      0010011
    // ALUsrc = ~instr[6];           //branch    1100011
    // ALUctrl = instr[14:12];      //          ||^ PCsrc
    // RegWrite = ~instr[6];        //          |^   not ALUsrc
    // ImmSrc = instr[6];          //          ^ not RegWrite 
    // end                          //          ALUctrl: funct3

endmodule

instr_rom.sv
module instr_rom 
// #(
//     parameter ADDRESS_WIDTH = 32, //should be in the same length as PC
//               DATA_WIDTH    = 8)
(
    input logic  [31:0]     addr,
    output logic [31:0]     dout

);

logic [7:0] rom_array [2**8-1:0]; //Theoretically, there should be 2^32 in memmory   
logic [7:0] short_addr;                 // but we do not need that many space, so I made to 
                                            // have only 256 memory spaces
//date width should be 8bit because it is a byte addressable memory
//so each instruction consist of four 8-bit byte

initial begin
        $display("Loading Instr_mem.");
        $readmemh("instruction.mem", rom_array);  //read instruction into rom
        // $display(rom_array [0], rom_array [1], rom_array [2],rom_array [3]);
end;

always_comb
    dout <= {rom_array [short_addr[7:0]+3], rom_array [short_addr[7:0]+2], rom_array [short_addr[7:0]+1],rom_array [short_addr[7:0]]};
    // dout <= 8'h11;

endmodule

counter_unit.sv
module counter_unit #(
    parameter PC_WIDTH = 32 // the length of pc and imme
)(
    input  logic clk,
    input  logic rst,
    input  logic PCsrc,
    // input  logic [PC_WIDTH-1:0] PC,
    input  logic [PC_WIDTH-1:0] ImmOp,
    output logic [PC_WIDTH-1:0] PC
);

// logic [PC_WIDTH-1:0] next_PC;
// logic [PC_WIDTH-1:0] branch_PC;

// assign branch_PC = PC + ImmOp;                                        //compute branch_pc
// assign next_PC = PCsrc ? branch_PC : PC + {{PC_WIDTH-1{1'b0}}, 1'b1};    //compute inc_PC

always_ff @ (posedge clk)begin
  if (rst)           PC <= 32'hBFC00000;
  else PC <= PCsrc ? PC + ImmOp : PC + 4;
  // else if (PCsrc)    PC <= PC + ImmOp;
  // else               PC <= PC + 4;
end


endmodule

top.sv
module top #(
    parameter D_WIDTH = 32,
              A_WIDTH = 5
)(
    input  logic        clk,
    input  logic        rst,
    output logic [16:0] a0
);

logic [D_WIDTH-1:0] PC;
logic [D_WIDTH-1:0] ImmOp;
logic               PCsrc;
logic               EQ;
logic               RegWrite;
logic               ALUctrl;
logic               ALUsrc;
logic               ResultSrc;
logic [1:0]         ImmSrc;
logic [A_WIDTH-1:0] AD1;
logic [A_WIDTH-1:0] AD2;
logic [A_WIDTH-1:0] AD3;
logic [D_WIDTH-1:0] RD1;
logic [D_WIDTH-1:0] RD2;
logic [D_WIDTH-1:0] ALUout;
logic [D_WIDTH-1:0] instr;
logic [D_WIDTH-1:0] out;

logic               Data_WE;
logic [D_WIDTH-1:0] Data_addr;
logic [D_WIDTH-1:0] Data_RD;



counter_unit pc_counter(
    .clk(clk),
    .rst(rst),
    .PCsrc(PCsrc),
    .ImmOp(ImmOp),
    .PC(PC)
);

instr_rom instr_mem(
    .addr(PC),
    .dout(instr)
);

control_unit encoder(
    .EQ(EQ),
    .instr(instr),
    .RegWrite(RegWrite),
    .ALUsrc(ALUsrc),
    .PCsrc(PCsrc),
    .ALUctrl(ALUctrl),
    .ImmSrc(ImmSrc),
    .ResultSrc(ResultSrc)
);

RegFile register_file(
    .clk(clk),
    .WE3(RegWrite),
    .AD1(instr[19:15]),
    .AD2(instr[24:20]),
    .AD3(instr[11:7]),
    .RD1(RD1),
    .RD2(RD2),
    .ALUout(ALUout),
    .Data_RD(Data_RD),
    .ResultSrc(ResultSrc),
    .a0(a0)
);

signextend extend(
    .instr(instr),
    .ImmSrc(ImmSrc),
    .ImmOp(ImmOp)
);

ALU_unit ALU(
    .ALUop1(RD1),
    .RegOp2(RD2),
    .ImmOp(ImmOp),
    .ALUctrl(ALUctrl),
    .ALUout(ALUout),
    .ALUsrc(ALUsrc),
    .EQ(EQ)
);

data_ram data_mem(
    .clk(clk),
    .Data_WE(Data_WE),
    .Data_addr(ALUout),
    .Data_RD(Data_RD),
    .Data_WD(RD2)
);



endmodule

top.vcd
$version Generated by VerilatedVcd $end
$date Tue Nov 22 21:32:14 2022 $end
$timescale 1ps $end

 $scope module TOP $end
  $var wire 17 ] a0 [16:0] $end
  $var wire  1 [ clk $end
  $var wire  1 \ rst $end
  $scope module top $end
   $var wire  5 ` AD1 [4:0] $end
   $var wire  5 a AD2 [4:0] $end
   $var wire  5 b AD3 [4:0] $end
   $var wire  1 ( ALUctrl $end
   $var wire 32 . ALUout [31:0] $end
   $var wire  1 ) ALUsrc $end
   $var wire 32 _ A_WIDTH [31:0] $end
   $var wire 32 ^ D_WIDTH [31:0] $end
   $var wire 32 0 Data_RD [31:0] $end
   $var wire  1 d Data_WE $end
   $var wire 32 e Data_addr [31:0] $end
   $var wire  1 & EQ $end
   $var wire 32 $ ImmOp [31:0] $end
   $var wire  2 + ImmSrc [1:0] $end
   $var wire 32 # PC [31:0] $end
   $var wire  1 % PCsrc $end
   $var wire 32 , RD1 [31:0] $end
   $var wire 32 - RD2 [31:0] $end
   $var wire  1 ' RegWrite $end
   $var wire  1 * ResultSrc $end
   $var wire 17 ] a0 [16:0] $end
   $var wire  1 [ clk $end
   $var wire 32 / instr [31:0] $end
   $var wire 32 c out [31:0] $end
   $var wire  1 \ rst $end
   $scope module ALU $end
    $var wire  3 1 ALUctrl [2:0] $end
    $var wire 32 , ALUop1 [31:0] $end
    $var wire 32 2 ALUop2 [31:0] $end
    $var wire 32 . ALUout [31:0] $end
    $var wire  1 ) ALUsrc $end
    $var wire  1 & EQ $end
    $var wire 32 $ ImmOp [31:0] $end
    $var wire 32 - RegOp2 [31:0] $end
    $var wire 32 ^ WIDTH [31:0] $end
   $upscope $end
   $scope module data_mem $end
    $var wire 32 0 Data_RD [31:0] $end
    $var wire 32 - Data_WD [31:0] $end
    $var wire  1 d Data_WE $end
    $var wire 32 . Data_addr [31:0] $end
    $var wire 32 ^ WIDTH [31:0] $end
    $var wire  1 [ clk $end
    $var wire  8 3 short_addr [7:0] $end
   $upscope $end
   $scope module encoder $end
    $var wire  3 4 ALUctrl [2:0] $end
    $var wire  1 ) ALUsrc $end
    $var wire  1 & EQ $end
    $var wire  2 + ImmSrc [1:0] $end
    $var wire  1 % PCsrc $end
    $var wire  1 ' RegWrite $end
    $var wire  1 * ResultSrc $end
    $var wire 32 ^ Wid [31:0] $end
    $var wire 32 / instr [31:0] $end
   $upscope $end
   $scope module extend $end
    $var wire 32 $ ImmOp [31:0] $end
    $var wire  2 + ImmSrc [1:0] $end
    $var wire 32 ^ Width [31:0] $end
    $var wire 32 / instr [31:0] $end
   $upscope $end
   $scope module instr_mem $end
    $var wire 32 # addr [31:0] $end
    $var wire 32 / dout [31:0] $end
    $var wire  8 5 short_addr [7:0] $end
   $upscope $end
   $scope module pc_counter $end
    $var wire 32 $ ImmOp [31:0] $end
    $var wire 32 # PC [31:0] $end
    $var wire 32 ^ PC_WIDTH [31:0] $end
    $var wire  1 % PCsrc $end
    $var wire  1 [ clk $end
    $var wire  1 \ rst $end
   $upscope $end
   $scope module register_file $end
    $var wire  5 6 AD1 [4:0] $end
    $var wire  5 7 AD2 [4:0] $end
    $var wire  5 8 AD3 [4:0] $end
    $var wire 32 . ALUout [31:0] $end
    $var wire 32 _ A_WIDTH [31:0] $end
    $var wire 32 ^ D_WIDTH [31:0] $end
    $var wire 32 0 Data_RD [31:0] $end
    $var wire 32 , RD1 [31:0] $end
    $var wire 32 - RD2 [31:0] $end
    $var wire  1 * ResultSrc $end
    $var wire 32 Z WD3 [31:0] $end
    $var wire  1 ' WE3 $end
    $var wire 32 9 a0 [31:0] $end
    $var wire  1 [ clk $end
    $var wire 32 : reg_file[0] [31:0] $end
    $var wire 32 D reg_file[10] [31:0] $end
    $var wire 32 E reg_file[11] [31:0] $end
    $var wire 32 F reg_file[12] [31:0] $end
    $var wire 32 G reg_file[13] [31:0] $end
    $var wire 32 H reg_file[14] [31:0] $end
    $var wire 32 I reg_file[15] [31:0] $end
    $var wire 32 J reg_file[16] [31:0] $end
    $var wire 32 K reg_file[17] [31:0] $end
    $var wire 32 L reg_file[18] [31:0] $end
    $var wire 32 M reg_file[19] [31:0] $end
    $var wire 32 ; reg_file[1] [31:0] $end
    $var wire 32 N reg_file[20] [31:0] $end
    $var wire 32 O reg_file[21] [31:0] $end
    $var wire 32 P reg_file[22] [31:0] $end
    $var wire 32 Q reg_file[23] [31:0] $end
    $var wire 32 R reg_file[24] [31:0] $end
    $var wire 32 S reg_file[25] [31:0] $end
    $var wire 32 T reg_file[26] [31:0] $end
    $var wire 32 U reg_file[27] [31:0] $end
    $var wire 32 V reg_file[28] [31:0] $end
    $var wire 32 W reg_file[29] [31:0] $end
    $var wire 32 < reg_file[2] [31:0] $end
    $var wire 32 X reg_file[30] [31:0] $end
    $var wire 32 Y reg_file[31] [31:0] $end
    $var wire 32 = reg_file[3] [31:0] $end
    $var wire 32 > reg_file[4] [31:0] $end
    $var wire 32 ? reg_file[5] [31:0] $end
    $var wire 32 @ reg_file[6] [31:0] $end
    $var wire 32 A reg_file[7] [31:0] $end
    $var wire 32 B reg_file[8] [31:0] $end
    $var wire 32 C reg_file[9] [31:0] $end
   $upscope $end
  $upscope $end
 $upscope $end
$enddefinitions $end


#0
b00000000000000000000000000000000 #
b00000000000000000000000000000000 $
0%
0&
0'
0(
0)
0*
b00 +
b00000000000000000000000000000000 ,
b00000000000000000000000000000000 -
b00000000000000000000000000000000 .
b00000000000000000000000000000000 /
b00000000000000000000000000000000 0
b000 1
b00000000000000000000000000000000 2
b00000000 3
b000 4
b00000000 5
b00000 6
b00000 7
b00000 8
b00000000000000000000000000000000 9
b00000000000000000000000000000000 :
b00000000000000000000000000000000 ;
b00000000000000000000000000000000 <
b00000000000000000000000000000000 =
b00000000000000000000000000000000 >
b00000000000000000000000000000000 ?
b00000000000000000000000000000000 @
b00000000000000000000000000000000 A
b00000000000000000000000000000000 B
b00000000000000000000000000000000 C
b00000000000000000000000000000000 D
b00000000000000000000000000000000 E
b00000000000000000000000000000000 F
b00000000000000000000000000000000 G
b00000000000000000000000000000000 H
b00000000000000000000000000000000 I
b00000000000000000000000000000000 J
b00000000000000000000000000000000 K
b00000000000000000000000000000000 L
b00000000000000000000000000000000 M
b00000000000000000000000000000000 N
b00000000000000000000000000000000 O
b00000000000000000000000000000000 P
b00000000000000000000000000000000 Q
b00000000000000000000000000000000 R
b00000000000000000000000000000000 S
b00000000000000000000000000000000 T
b00000000000000000000000000000000 U
b00000000000000000000000000000000 V
b00000000000000000000000000000000 W
b00000000000000000000000000000000 X
b00000000000000000000000000000000 Y
b00000000000000000000000000000000 Z
0[
0\
b00000000000000000 ]
b00000000000000000000000000100000 ^
b00000000000000000000000000000101 _
b00000 `
b00000 a
b00000 b
b00000000000000000000000000000000 c
0d
b00000000000000000000000000000000 e
#1
1&
1'
1)
1*
b00000000000000000010001100000011 /
b00010001001000100011001101000100 0
b010 4
b00110 8
b00010001001000100011001101000100 Z
1[
#2
0[
1\
#3
b00010001001000100011001101000100 @
1[
#4
0[
0\
#5
b00000000000000000000000000000100 #
b00000000000000000000000000000100 $
0&
b00000000000000000000000000000100 .
b00000000010000000010001110000011 /
b01010101011001100111011110001000 0
b00000000000000000000000000000100 2
b00000100 3
b00000100 5
b00100 7
b00111 8
b01010101011001100111011110001000 Z
1[
#6
0[
#7
b00000000000000000000000000001000 #
b00000000000000000000000000000000 $
1&
0'
0)
0*
b00000000000000000000000000000000 .
b00000000000000000000000000000000 /
b00010001001000100011001101000100 0
b00000000000000000000000000000000 2
b00000000 3
b000 4
b00001000 5
b00000 7
b00000 8
b01010101011001100111011110001000 A
b00000000000000000000000000000000 Z
1[
#8
0[
#9
b00000000000000000000000000001100 #
b00001100 5
1[
#10
0[
#11
b00000000000000000000000000010000 #
b00010000 5
1[
#12
0[
#13
b00000000000000000000000000010100 #
b00010100 5
1[
#14
0[
#15
b00000000000000000000000000011000 #
b00011000 5
1[
#16
0[
#17
b00000000000000000000000000011100 #
b00011100 5
1[
#18
0[
#19
b00000000000000000000000000100000 #
b00100000 5
1[
#20
0[
#21
b00000000000000000000000000100100 #
b00100100 5
1[
#22
0[
#23
b00000000000000000000000000101000 #
b00101000 5
1[
#24
0[
#25
b00000000000000000000000000101100 #
b00101100 5
1[
#26
0[
#27
b00000000000000000000000000110000 #
b00110000 5
1[
#28
0[
#29
b00000000000000000000000000110100 #
b00110100 5
1[
#30
0[
#31
b00000000000000000000000000111000 #
b00111000 5
1[
#32
0[
#33
b00000000000000000000000000111100 #
b00111100 5
1[
#34
0[
#35
b00000000000000000000000001000000 #
b01000000 5
1[
#36
0[
#37
b00000000000000000000000001000100 #
b01000100 5
1[
#38
0[
#39
b00000000000000000000000001001000 #
b01001000 5
1[
#40
0[
#41
b00000000000000000000000001001100 #
b01001100 5
1[
#42
0[
#43
b00000000000000000000000001010000 #
b01010000 5
1[
#44
0[
#45
b00000000000000000000000001010100 #
b01010100 5
1[
#46
0[
#47
b00000000000000000000000001011000 #
b01011000 5
1[
#48
0[
#49
b00000000000000000000000001011100 #
b01011100 5
1[
#50
0[
#51
b00000000000000000000000001100000 #
b01100000 5
1[
#52
0[
#53
b00000000000000000000000001100100 #
b01100100 5
1[
#54
0[
#55
b00000000000000000000000001101000 #
b01101000 5
1[
#56
0[
#57
b00000000000000000000000001101100 #
b01101100 5
1[
#58
0[
#59
b00000000000000000000000001110000 #
b01110000 5
1[
#60
0[
#61
b00000000000000000000000001110100 #
b01110100 5
1[
#62
0[
#63
b00000000000000000000000001111000 #
b01111000 5
1[
#64
0[
#65
b00000000000000000000000001111100 #
b01111100 5
1[
#66
0[
#67
b00000000000000000000000010000000 #
b10000000 5
1[
#68
0[
#69
b00000000000000000000000010000100 #
b10000100 5
1[
#70
0[
#71
b00000000000000000000000010001000 #
b10001000 5
1[
#72
0[
#73
b00000000000000000000000010001100 #
b10001100 5
1[
#74
0[
#75
b00000000000000000000000010010000 #
b10010000 5
1[
#76
0[
#77
b00000000000000000000000010010100 #
b10010100 5
1[
#78
0[
#79
b00000000000000000000000010011000 #
b10011000 5
1[
#80
0[
#81
b00000000000000000000000010011100 #
b10011100 5
1[
#82
0[
#83
b00000000000000000000000010100000 #
b10100000 5
1[
#84
0[
#85
b00000000000000000000000010100100 #
b10100100 5
1[
#86
0[
#87
b00000000000000000000000010101000 #
b10101000 5
1[
#88
0[
#89
b00000000000000000000000010101100 #
b10101100 5
1[
#90
0[
#91
b00000000000000000000000010110000 #
b10110000 5
1[
#92
0[
#93
b00000000000000000000000010110100 #
b10110100 5
1[
#94
0[
#95
b00000000000000000000000010111000 #
b10111000 5
1[
#96
0[
#97
b00000000000000000000000010111100 #
b10111100 5
1[
#98
0[
#99
b00000000000000000000000011000000 #
b11000000 5
1[
#100
0[
#101
b00000000000000000000000011000100 #
b11000100 5
1[
#102
0[
#103
b00000000000000000000000011001000 #
b11001000 5
1[
#104
0[
#105
b00000000000000000000000011001100 #
b11001100 5
1[
#106
0[
#107
b00000000000000000000000011010000 #
b11010000 5
1[
#108
0[
#109
b00000000000000000000000011010100 #
b11010100 5
1[
#110
0[
#111
b00000000000000000000000011011000 #
b11011000 5
1[
#112
0[
#113
b00000000000000000000000011011100 #
b11011100 5
1[
#114
0[
#115
b00000000000000000000000011100000 #
b11100000 5
1[
#116
0[
#117
b00000000000000000000000011100100 #
b11100100 5
1[
#118
0[
#119
b00000000000000000000000011101000 #
b11101000 5
1[
#120
0[
#121
b00000000000000000000000011101100 #
b11101100 5
1[
#122
0[
#123
b00000000000000000000000011110000 #
b11110000 5
1[
#124
0[
#125
b00000000000000000000000011110100 #
b11110100 5
1[
#126
0[
#127
b00000000000000000000000011111000 #
b11111000 5
1[
#128
0[
#129
b00000000000000000000000011111100 #
b11111100 5
1[
#130
0[
#131
b00000000000000000000000100000000 #
1'
1)
1*
b00000000000000000010001100000011 /
b010 4
b00000000 5
b00110 8
b00010001001000100011001101000100 Z
1[
#132
0[
#133
b00000000000000000000000100000100 #
b00000000000000000000000000000100 $
0&
b00000000000000000000000000000100 .
b00000000010000000010001110000011 /
b01010101011001100111011110001000 0
b00000000000000000000000000000100 2
b00000100 3
b00000100 5
b00100 7
b00111 8
b01010101011001100111011110001000 Z
1[
#134
0[
#135
b00000000000000000000000100001000 #
b00000000000000000000000000000000 $
1&
0'
0)
0*
b00000000000000000000000000000000 .
b00000000000000000000000000000000 /
b00010001001000100011001101000100 0
b00000000000000000000000000000000 2
b00000000 3
b000 4
b00001000 5
b00000 7
b00000 8
b00000000000000000000000000000000 Z
1[
#136
0[
#137
b00000000000000000000000100001100 #
b00001100 5
1[
#138
0[
#139
b00000000000000000000000100010000 #
b00010000 5
1[
#140
0[
#141
b00000000000000000000000100010100 #
b00010100 5
1[
#142
0[
#143
b00000000000000000000000100011000 #
b00011000 5
1[
#144
0[
#145
b00000000000000000000000100011100 #
b00011100 5
1[
#146
0[
#147
b00000000000000000000000100100000 #
b00100000 5
1[
#148
0[
#149
b00000000000000000000000100100100 #
b00100100 5
1[
#150
0[
#151
b00000000000000000000000100101000 #
b00101000 5
1[
#152
0[
#153
b00000000000000000000000100101100 #
b00101100 5
1[
#154
0[
#155
b00000000000000000000000100110000 #
b00110000 5
1[
#156
0[
#157
b00000000000000000000000100110100 #
b00110100 5
1[
#158
0[
#159
b00000000000000000000000100111000 #
b00111000 5
1[
#160
0[
#161
b00000000000000000000000100111100 #
b00111100 5
1[
#162
0[
#163
b00000000000000000000000101000000 #
b01000000 5
1[
#164
0[
#165
b00000000000000000000000101000100 #
b01000100 5
1[
#166
0[
#167
b00000000000000000000000101001000 #
b01001000 5
1[
#168
0[
#169
b00000000000000000000000101001100 #
b01001100 5
1[
#170
0[
#171
b00000000000000000000000101010000 #
b01010000 5
1[
#172
0[
#173
b00000000000000000000000101010100 #
b01010100 5
1[
#174
0[
#175
b00000000000000000000000101011000 #
b01011000 5
1[
#176
0[
#177
b00000000000000000000000101011100 #
b01011100 5
1[
#178
0[
#179
b00000000000000000000000101100000 #
b01100000 5
1[
#180
0[
#181
b00000000000000000000000101100100 #
b01100100 5
1[
#182
0[
#183
b00000000000000000000000101101000 #
b01101000 5
1[
#184
0[
#185
b00000000000000000000000101101100 #
b01101100 5
1[
#186
0[
#187
b00000000000000000000000101110000 #
b01110000 5
1[
#188
0[
#189
b00000000000000000000000101110100 #
b01110100 5
1[
#190
0[
#191
b00000000000000000000000101111000 #
b01111000 5
1[
#192
0[
#193
b00000000000000000000000101111100 #
b01111100 5
1[
#194
0[
#195
b00000000000000000000000110000000 #
b10000000 5
1[
#196
0[
#197
b00000000000000000000000110000100 #
b10000100 5
1[
#198
0[
#199
b00000000000000000000000110001000 #
b10001000 5
1[
#200
0[
#201
b00000000000000000000000110001100 #
b10001100 5
1[
#202
0[
#203
b00000000000000000000000110010000 #
b10010000 5
1[
#204
0[
#205
b00000000000000000000000110010100 #
b10010100 5
1[
#206
0[
#207
b00000000000000000000000110011000 #
b10011000 5
1[
#208
0[
#209
b00000000000000000000000110011100 #
b10011100 5
1[
#210
0[
#211
b00000000000000000000000110100000 #
b10100000 5
1[
#212
0[
#213
b00000000000000000000000110100100 #
b10100100 5
1[
#214
0[
#215
b00000000000000000000000110101000 #
b10101000 5
1[
#216
0[
#217
b00000000000000000000000110101100 #
b10101100 5
1[
#218
0[
#219
b00000000000000000000000110110000 #
b10110000 5
1[
#220
0[
#221
b00000000000000000000000110110100 #
b10110100 5
1[
#222
0[
#223
b00000000000000000000000110111000 #
b10111000 5
1[
#224
0[
#225
b00000000000000000000000110111100 #
b10111100 5
1[
#226
0[
#227
b00000000000000000000000111000000 #
b11000000 5
1[
#228
0[
#229
b00000000000000000000000111000100 #
b11000100 5
1[
#230
0[
#231
b00000000000000000000000111001000 #
b11001000 5
1[
#232
0[
#233
b00000000000000000000000111001100 #
b11001100 5
1[
#234
0[
#235
b00000000000000000000000111010000 #
b11010000 5
1[
#236
0[
#237
b00000000000000000000000111010100 #
b11010100 5
1[
#238
0[
#239
b00000000000000000000000111011000 #
b11011000 5
1[
#240
0[
#241
b00000000000000000000000111011100 #
b11011100 5
1[
#242
0[
#243
b00000000000000000000000111100000 #
b11100000 5
1[
#244
0[
#245
b00000000000000000000000111100100 #
b11100100 5
1[
#246
0[
#247
b00000000000000000000000111101000 #
b11101000 5
1[
#248
0[
#249
b00000000000000000000000111101100 #
b11101100 5
1[
#250
0[
#251
b00000000000000000000000111110000 #
b11110000 5
1[
#252
0[
#253
b00000000000000000000000111110100 #
b11110100 5
1[
#254
0[
#255
b00000000000000000000000111111000 #
b11111000 5
1[
#256
0[
#257
b00000000000000000000000111111100 #
b11111100 5
1[
#258
0[
#259
b00000000000000000000001000000000 #
1'
1)
1*
b00000000000000000010001100000011 /
b010 4
b00000000 5
b00110 8
b00010001001000100011001101000100 Z
1[
#260
0[
#261
b00000000000000000000001000000100 #
b00000000000000000000000000000100 $
0&
b00000000000000000000000000000100 .
b00000000010000000010001110000011 /
b01010101011001100111011110001000 0
b00000000000000000000000000000100 2
b00000100 3
b00000100 5
b00100 7
b00111 8
b01010101011001100111011110001000 Z
1[
#262
0[
#263
b00000000000000000000001000001000 #
b00000000000000000000000000000000 $
1&
0'
0)
0*
b00000000000000000000000000000000 .
b00000000000000000000000000000000 /
b00010001001000100011001101000100 0
b00000000000000000000000000000000 2
b00000000 3
b000 4
b00001000 5
b00000 7
b00000 8
b00000000000000000000000000000000 Z
1[
#264
0[
#265
b00000000000000000000001000001100 #
b00001100 5
1[
#266
0[
#267
b00000000000000000000001000010000 #
b00010000 5
1[
#268
0[
#269
b00000000000000000000001000010100 #
b00010100 5
1[
#270
0[
#271
b00000000000000000000001000011000 #
b00011000 5
1[
#272
0[
#273
b00000000000000000000001000011100 #
b00011100 5
1[
#274
0[
#275
b00000000000000000000001000100000 #
b00100000 5
1[
#276
0[
#277
b00000000000000000000001000100100 #
b00100100 5
1[
#278
0[
#279
b00000000000000000000001000101000 #
b00101000 5
1[
#280
0[
#281
b00000000000000000000001000101100 #
b00101100 5
1[
#282
0[
#283
b00000000000000000000001000110000 #
b00110000 5
1[
#284
0[
#285
b00000000000000000000001000110100 #
b00110100 5
1[
#286
0[
#287
b00000000000000000000001000111000 #
b00111000 5
1[
#288
0[
#289
b00000000000000000000001000111100 #
b00111100 5
1[
#290
0[
#291
b00000000000000000000001001000000 #
b01000000 5
1[
#292
0[
#293
b00000000000000000000001001000100 #
b01000100 5
1[
#294
0[
#295
b00000000000000000000001001001000 #
b01001000 5
1[
#296
0[
#297
b00000000000000000000001001001100 #
b01001100 5
1[
#298
0[
#299
b00000000000000000000001001010000 #
b01010000 5
1[
#300
0[
#301
b00000000000000000000001001010100 #
b01010100 5
1[
#302
0[
#303
b00000000000000000000001001011000 #
b01011000 5
1[
#304
0[
#305
b00000000000000000000001001011100 #
b01011100 5
1[
#306
0[
#307
b00000000000000000000001001100000 #
b01100000 5
1[
#308
0[
#309
b00000000000000000000001001100100 #
b01100100 5
1[
#310
0[
#311
b00000000000000000000001001101000 #
b01101000 5
1[
#312
0[
#313
b00000000000000000000001001101100 #
b01101100 5
1[
#314
0[
#315
b00000000000000000000001001110000 #
b01110000 5
1[
#316
0[
#317
b00000000000000000000001001110100 #
b01110100 5
1[
#318
0[
#319
b00000000000000000000001001111000 #
b01111000 5
1[
#320
0[
#321
b00000000000000000000001001111100 #
b01111100 5
1[
#322
0[
#323
b00000000000000000000001010000000 #
b10000000 5
1[
#324
0[
#325
b00000000000000000000001010000100 #
b10000100 5
1[
#326
0[
#327
b00000000000000000000001010001000 #
b10001000 5
1[
#328
0[
#329
b00000000000000000000001010001100 #
b10001100 5
1[
#330
0[
#331
b00000000000000000000001010010000 #
b10010000 5
1[
#332
0[
#333
b00000000000000000000001010010100 #
b10010100 5
1[
#334
0[
#335
b00000000000000000000001010011000 #
b10011000 5
1[
#336
0[
#337
b00000000000000000000001010011100 #
b10011100 5
1[
#338
0[
#339
b00000000000000000000001010100000 #
b10100000 5
1[
#340
0[
#341
b00000000000000000000001010100100 #
b10100100 5
1[
#342
0[
#343
b00000000000000000000001010101000 #
b10101000 5
1[
#344
0[
#345
b00000000000000000000001010101100 #
b10101100 5
1[
#346
0[
#347
b00000000000000000000001010110000 #
b10110000 5
1[
#348
0[
#349
b00000000000000000000001010110100 #
b10110100 5
1[
#350
0[
#351
b00000000000000000000001010111000 #
b10111000 5
1[
#352
0[
#353
b00000000000000000000001010111100 #
b10111100 5
1[
#354
0[
#355
b00000000000000000000001011000000 #
b11000000 5
1[
#356
0[
#357
b00000000000000000000001011000100 #
b11000100 5
1[
#358
0[
#359
b00000000000000000000001011001000 #
b11001000 5
1[
#360
0[
#361
b00000000000000000000001011001100 #
b11001100 5
1[
#362
0[
#363
b00000000000000000000001011010000 #
b11010000 5
1[
#364
0[
#365
b00000000000000000000001011010100 #
b11010100 5
1[
#366
0[
#367
b00000000000000000000001011011000 #
b11011000 5
1[
#368
0[
#369
b00000000000000000000001011011100 #
b11011100 5
1[
#370
0[
#371
b00000000000000000000001011100000 #
b11100000 5
1[
#372
0[
#373
b00000000000000000000001011100100 #
b11100100 5
1[
#374
0[
