ALU_unit.sv
module ALU_unit #(
    parameter WIDTH = 32
)(
    input   logic [WIDTH-1:0] ALUop1,
    input   logic [WIDTH-1:0] RegOp2,
    input   logic [WIDTH-1:0] ImmOp,
    output  logic [WIDTH-1:0] ALUout,
    input   logic [2:0]       ALUctrl,
    input   logic             ALUsrc,
    output  logic             EQ
);

logic [WIDTH-1:0] ALUop2;

always_comb begin
    ALUop2 = ALUsrc ? ImmOp : RegOp2;
    ALUout = ALUctrl[0] ? ALUop1 - ALUop2 : ALUop1 + ALUop2;
    EQ = (ALUop1 == ALUop2);
end

endmodule

signextend.sv
module signextend #(
    parameter Width = 32
)(
    input  logic [Width-1:0] instr,
    input  logic             ImmSrc,  //should be instr[4]
    output logic [Width-1:0] ImmOp
);


assign ImmOp = ImmSrc ? { {20{instr[31]}}, instr[31:20] } : { {20{instr[31]}}, instr[31], instr[7], instr[30:25], instr[11:8] }; //{instr[31], instr[7], instr[30:25], instr[11:8]};     

    // assign a = {20'hFFFFF, instr}
    // assign b = {20'h0, instr}  
   

    // assign ImmOp = ImmSrc ? a : b;
endmodule

RegFile.sv
module RegFile #(
    parameter D_WIDTH = 32,
              A_WIDTH = 5
)(
    input logic clk,
    input logic WE3,
    input logic [A_WIDTH-1:0] AD1,
    input logic [A_WIDTH-1:0] AD2,
    input logic [A_WIDTH-1:0] AD3,
    input logic [D_WIDTH-1:0] WD3,
    output logic [D_WIDTH-1:0] RD1,
    output logic [D_WIDTH-1:0] RD2,
    output logic [D_WIDTH-1:0] a0
);

reg [D_WIDTH-1:0] reg_file [31:0];



// initial begin
//     // for (i = 0; i < 2**A_WIDTH -1; i++){
//     //     reg_file[i] <= 32'b0
//     // }
//     $display("Loading RegFile.");
//     $readmemh("RegFile.mem", reg_file);
// end;
assign reg_file[0] = 32'b0;

always_ff @( posedge clk ) begin 

    if (WE3) reg_file[AD3] = WD3;
    
end

always_comb begin
    RD1 = reg_file[AD1];
    RD2 = reg_file[AD2];
    a0 <= reg_file[0];
end

endmodule

control_unit.sv
module control_unit #(
    parameter Wid = 32
)(
    input  logic           EQ,
    input  logic [Wid-1:0] instr,
    output logic           RegWrite,
    output logic           ALUsrc,
    output logic           PCsrc,
    output logic [2:0]     ALUctrl,
    output logic           ImmSrc
);

always_comb

    case(instr[6:0])
    7'b0010011:begin //addi
    RegWrite = 1;
    ImmSrc = 1;
    ALUsrc = 1;
    end

    7'b1100011:begin //bne
    RegWrite = 0;
    PCsrc = ~EQ;
    ImmSrc = 1;
    ALUsrc = 0;
    end

    7'b0000001:begin //load
    RegWrite = 1;
    ImmSrc = 1;
    ALUsrc = 1;
    end

    default:begin
    ALUctrl = instr[14:12];
    ImmSrc = 1;
    PCsrc = 0;
    end

    endcase





    // begin                        // add      0110011
    // PCsrc = instr[6];            //addi      0010011
    // ALUsrc = ~instr[6];           //branch    1100011
    // ALUctrl = instr[14:12];      //          ||^ PCsrc
    // RegWrite = ~instr[6];        //          |^   not ALUsrc
    // ImmSrc = instr[6];          //          ^ not RegWrite 
    // end                          //          ALUctrl: funct3

endmodule





// 000 0011 load
// 001 0011 addi
// 110 0011 bne
// ^^ ~RegWrite
// ^^ PCsrc
// ^^ ~ALUsrc
// ^^ ~Immsrc

instr_rom.sv
module instr_rom 
// #(
//     parameter ADDRESS_WIDTH = 32, //should be in the same length as PC
//               DATA_WIDTH    = 8)
(
    input logic  [31:0]     addr,
    output logic [31:0]     dout

);

logic [7:0] rom_array [2**8-1:0]; //Theoretically, there should be 2^32 in memmory   
logic [7:0] short_addr;                 // but we do not need that many space, so I made to 
                                            // have only 256 memory spaces
//date width should be 8bit because it is a byte addressable memory
//so each instruction consist of four 8-bit byte

initial begin
        $display("Loading Instr_mem.");
        $readmemh("instruction.mem", rom_array);  //read instruction into rom
        // $display(rom_array [0], rom_array [1], rom_array [2],rom_array [3]);
end;

assign short_addr = addr[7:0];
always_comb
    dout <= {rom_array [short_addr[7:0]], rom_array [short_addr[7:0]+1], rom_array [short_addr[7:0]+2],rom_array [short_addr[7:0]+3]};
    // dout <= 8'h11;

endmodule

counter_unit.sv
module counter_unit #(
    parameter PC_WIDTH = 32 // the length of pc and imme
)(
    input  logic clk,
    input  logic rst,
    input  logic PCsrc,
    // input  logic [PC_WIDTH-1:0] PC,
    input  logic [PC_WIDTH-1:0] ImmOp,
    output logic [PC_WIDTH-1:0] PC
);

// logic [PC_WIDTH-1:0] next_PC;
// logic [PC_WIDTH-1:0] branch_PC;

// assign branch_PC = PC + ImmOp;                                        //compute branch_pc
// assign next_PC = PCsrc ? branch_PC : PC + {{PC_WIDTH-1{1'b0}}, 1'b1};    //compute inc_PC

always_ff @ (posedge clk)begin
  if (rst)           PC <= 32'hBFC00000;
  else PC <= PCsrc ? PC + ImmOp : PC + 4;
  // else if (PCsrc)    PC <= PC + ImmOp;
  // else               PC <= PC + 4;
end


endmodule

top.sv
module top #(
    parameter D_WIDTH = 32,
              A_WIDTH = 5
)(
    input  logic        clk,
    input  logic        rst,
    output logic [16:0] a0
);

logic [D_WIDTH-1:0] PC;
logic [D_WIDTH-1:0] ImmOp;
logic PCsrc;
logic EQ;
logic RegWrite;
logic ALUctrl;
logic ALUsrc;
logic ImmSrc;
logic [A_WIDTH-1:0] AD1;
logic [A_WIDTH-1:0] AD2;
logic [A_WIDTH-1:0] AD3;
logic [A_WIDTH-1:0] WD3;
logic [D_WIDTH-1:0] RD1;
logic [D_WIDTH-1:0] RD2;
logic [D_WIDTH-1:0] ALUout;
logic [D_WIDTH-1:0] instr;
logic [D_WIDTH-1:0] out;


counter_unit pc_counter(
    .clk(clk),
    .rst(rst),
    .PCsrc(PCsrc),
    .ImmOp(ImmOp),
    .PC(PC)
);

instr_rom instr_mem(
    .addr(PC),
    .dout(instr)
);

control_unit encoder(
    .EQ(EQ),
    .instr(instr),
    .RegWrite(RegWrite),
    .ALUsrc(ALUsrc),
    .PCsrc(PCsrc),
    .ALUctrl(ALUctrl),
    .ImmSrc(ImmSrc)
);

RegFile register_file(
    .clk(clk),
    .WE3(RegWrite),
    .AD1(instr[19:15]),
    .AD2(instr[24:20]),
    .AD3(instr[11:7]),
    .RD1(RD1),
    .RD2(RD2),
    .WD3(ALUout),
    .a0(a0)
);

signextend extend(
    .instr(instr),
    .ImmSrc(ImmSrc),
    .ImmOp(ImmOp)
);

ALU_unit ALU(
    .ALUop1(RD1),
    .RegOp2(RD2),
    .ImmOp(ImmOp),
    .ALUctrl(ALUctrl),
    .ALUout(ALUout),
    .ALUsrc(ALUsrc),
    .EQ(EQ)
);



endmodule

top.vcd
$version Generated by VerilatedVcd $end
$date Mon Nov 21 23:39:07 2022 $end
$timescale 1ps $end

 $scope module TOP $end
  $var wire 17 Y a0 [16:0] $end
  $var wire  1 W clk $end
  $var wire  1 X rst $end
  $scope module top $end
   $var wire  5 \ AD1 [4:0] $end
   $var wire  5 ] AD2 [4:0] $end
   $var wire  5 ^ AD3 [4:0] $end
   $var wire  1 ) ALUctrl $end
   $var wire 32 - ALUout [31:0] $end
   $var wire  1 * ALUsrc $end
   $var wire 32 [ A_WIDTH [31:0] $end
   $var wire 32 Z D_WIDTH [31:0] $end
   $var wire  1 ' EQ $end
   $var wire 32 % ImmOp [31:0] $end
   $var wire  1 # ImmSrc $end
   $var wire 32 $ PC [31:0] $end
   $var wire  1 & PCsrc $end
   $var wire 32 + RD1 [31:0] $end
   $var wire 32 , RD2 [31:0] $end
   $var wire  1 ( RegWrite $end
   $var wire  5 _ WD3 [4:0] $end
   $var wire 17 Y a0 [16:0] $end
   $var wire  1 W clk $end
   $var wire 32 . instr [31:0] $end
   $var wire 32 ` out [31:0] $end
   $var wire  1 X rst $end
   $scope module ALU $end
    $var wire  3 / ALUctrl [2:0] $end
    $var wire 32 + ALUop1 [31:0] $end
    $var wire 32 0 ALUop2 [31:0] $end
    $var wire 32 - ALUout [31:0] $end
    $var wire  1 * ALUsrc $end
    $var wire  1 ' EQ $end
    $var wire 32 % ImmOp [31:0] $end
    $var wire 32 , RegOp2 [31:0] $end
    $var wire 32 Z WIDTH [31:0] $end
   $upscope $end
   $scope module encoder $end
    $var wire  3 1 ALUctrl [2:0] $end
    $var wire  1 * ALUsrc $end
    $var wire  1 ' EQ $end
    $var wire  1 # ImmSrc $end
    $var wire  1 & PCsrc $end
    $var wire  1 ( RegWrite $end
    $var wire 32 Z Wid [31:0] $end
    $var wire 32 . instr [31:0] $end
   $upscope $end
   $scope module extend $end
    $var wire 32 % ImmOp [31:0] $end
    $var wire  1 # ImmSrc $end
    $var wire 32 Z Width [31:0] $end
    $var wire 32 . instr [31:0] $end
   $upscope $end
   $scope module instr_mem $end
    $var wire 32 $ addr [31:0] $end
    $var wire 32 . dout [31:0] $end
    $var wire  8 2 short_addr [7:0] $end
   $upscope $end
   $scope module pc_counter $end
    $var wire 32 % ImmOp [31:0] $end
    $var wire 32 $ PC [31:0] $end
    $var wire 32 Z PC_WIDTH [31:0] $end
    $var wire  1 & PCsrc $end
    $var wire  1 W clk $end
    $var wire  1 X rst $end
   $upscope $end
   $scope module register_file $end
    $var wire  5 3 AD1 [4:0] $end
    $var wire  5 4 AD2 [4:0] $end
    $var wire  5 5 AD3 [4:0] $end
    $var wire 32 [ A_WIDTH [31:0] $end
    $var wire 32 Z D_WIDTH [31:0] $end
    $var wire 32 + RD1 [31:0] $end
    $var wire 32 , RD2 [31:0] $end
    $var wire 32 - WD3 [31:0] $end
    $var wire  1 ( WE3 $end
    $var wire 32 6 a0 [31:0] $end
    $var wire  1 W clk $end
    $var wire 32 7 reg_file[0] [31:0] $end
    $var wire 32 A reg_file[10] [31:0] $end
    $var wire 32 B reg_file[11] [31:0] $end
    $var wire 32 C reg_file[12] [31:0] $end
    $var wire 32 D reg_file[13] [31:0] $end
    $var wire 32 E reg_file[14] [31:0] $end
    $var wire 32 F reg_file[15] [31:0] $end
    $var wire 32 G reg_file[16] [31:0] $end
    $var wire 32 H reg_file[17] [31:0] $end
    $var wire 32 I reg_file[18] [31:0] $end
    $var wire 32 J reg_file[19] [31:0] $end
    $var wire 32 8 reg_file[1] [31:0] $end
    $var wire 32 K reg_file[20] [31:0] $end
    $var wire 32 L reg_file[21] [31:0] $end
    $var wire 32 M reg_file[22] [31:0] $end
    $var wire 32 N reg_file[23] [31:0] $end
    $var wire 32 O reg_file[24] [31:0] $end
    $var wire 32 P reg_file[25] [31:0] $end
    $var wire 32 Q reg_file[26] [31:0] $end
    $var wire 32 R reg_file[27] [31:0] $end
    $var wire 32 S reg_file[28] [31:0] $end
    $var wire 32 T reg_file[29] [31:0] $end
    $var wire 32 9 reg_file[2] [31:0] $end
    $var wire 32 U reg_file[30] [31:0] $end
    $var wire 32 V reg_file[31] [31:0] $end
    $var wire 32 : reg_file[3] [31:0] $end
    $var wire 32 ; reg_file[4] [31:0] $end
    $var wire 32 < reg_file[5] [31:0] $end
    $var wire 32 = reg_file[6] [31:0] $end
    $var wire 32 > reg_file[7] [31:0] $end
    $var wire 32 ? reg_file[8] [31:0] $end
    $var wire 32 @ reg_file[9] [31:0] $end
   $upscope $end
  $upscope $end
 $upscope $end
$enddefinitions $end


#0
0#
b00000000000000000000000000000000 $
b00000000000000000000000000000000 %
0&
0'
0(
0)
0*
b00000000000000000000000000000000 +
b00000000000000000000000000000000 ,
b00000000000000000000000000000000 -
b00000000000000000000000000000000 .
b000 /
b00000000000000000000000000000000 0
b000 1
b00000000 2
b00000 3
b00000 4
b00000 5
b00000000000000000000000000000000 6
b00000000000000000000000000000000 7
b00000000000000000000000000000000 8
b00000000000000000000000000000000 9
b00000000000000000000000000000000 :
b00000000000000000000000000000000 ;
b00000000000000000000000000000000 <
b00000000000000000000000000000000 =
b00000000000000000000000000000000 >
b00000000000000000000000000000000 ?
b00000000000000000000000000000000 @
b00000000000000000000000000000000 A
b00000000000000000000000000000000 B
b00000000000000000000000000000000 C
b00000000000000000000000000000000 D
b00000000000000000000000000000000 E
b00000000000000000000000000000000 F
b00000000000000000000000000000000 G
b00000000000000000000000000000000 H
b00000000000000000000000000000000 I
b00000000000000000000000000000000 J
b00000000000000000000000000000000 K
b00000000000000000000000000000000 L
b00000000000000000000000000000000 M
b00000000000000000000000000000000 N
b00000000000000000000000000000000 O
b00000000000000000000000000000000 P
b00000000000000000000000000000000 Q
b00000000000000000000000000000000 R
b00000000000000000000000000000000 S
b00000000000000000000000000000000 T
b00000000000000000000000000000000 U
b00000000000000000000000000000000 V
0W
0X
b00000000000000000 Y
b00000000000000000000000000100000 Z
b00000000000000000000000000000101 [
b00000 \
b00000 ]
b00000 ^
b00000 _
b00000000000000000000000000000000 `
#1
1#
b00000000000000000000000011111111 %
1(
1*
b00000000000000000000000011111111 -
b00001111111100000000001100010011 .
b00000000000000000000000011111111 0
b11111 4
b00110 5
1W
#2
0W
1X
#3
b00000000000000000000000011111111 =
1W
#4
0W
0X
#5
b00000000000000000000000000000100 $
b00000000000000000000000000000000 %
1'
b00000000000000000000000000000000 -
b00000000000000000000010100010011 .
b00000000000000000000000000000000 0
b00000100 2
b00000 4
b01010 5
1W
#6
0W
#7
b00000000000000000000000000001000 $
b00000000000000000000010110010011 .
b00001000 2
b01011 5
1W
#8
0W
#9
b00000000000000000000000000001100 $
b00000000000001011000010100010011 .
b00001100 2
b01011 3
b01010 5
1W
#10
0W
#11
b00000000000000000000000000010000 $
b00000000000000000000000000000001 %
0'
b00000000000000000000000000000001 -
b00000000000101011000010110010011 .
b00000000000000000000000000000001 0
b00010000 2
b00001 4
b01011 5
1W
#12
0W
#13
b00000000000000000000000000010100 $
b11111111111111111111111111100110 %
1'
0(
0*
b00000000000000000000000000000000 -
b11111110011001011001110011100011 .
b00000000000000000000000000000000 0
b00010100 2
b00110 4
b11001 5
b00000000000000000000000000000001 B
1W
#14
0W
#15
b00000000000000000000000000011000 $
b11111111111111111111111111100000 %
0'
1)
b00000000000000000000000000000001 +
b00000000000000000000000011111111 ,
b11111111111111111111111100000010 -
b11111110000000110001100000000000 .
b001 /
b00000000000000000000000011111111 0
b001 1
b00011000 2
b00110 3
b00000 4
b10000 5
1W
#16
0W
#17
b00000000000000000000000000011100 $
b00000000000000000000000000000000 %
0)
b00000000000000000000000011111111 +
b00000000000000000000000000000000 ,
b00000000000000000000000011111111 -
b00000000000000000000000000000000 .
b000 /
b00000000000000000000000000000000 0
b000 1
b00011100 2
b00000 3
b00000 5
1W
#18
0W
#19
b00000000000000000000000000100000 $
1'
b00000000000000000000000000000000 +
b00000000000000000000000000000000 -
b00100000 2
1W
#20
0W
#21
b00000000000000000000000000100100 $
b00100100 2
1W
#22
0W
#23
b00000000000000000000000000101000 $
b00101000 2
1W
#24
0W
#25
b00000000000000000000000000101100 $
b00101100 2
1W
#26
0W
#27
b00000000000000000000000000110000 $
b00110000 2
1W
#28
0W
#29
b00000000000000000000000000110100 $
b00110100 2
1W
#30
0W
#31
b00000000000000000000000000111000 $
b00111000 2
1W
#32
0W
#33
b00000000000000000000000000111100 $
b00111100 2
1W
#34
0W
#35
b00000000000000000000000001000000 $
b01000000 2
1W
#36
0W
#37
b00000000000000000000000001000100 $
b01000100 2
1W
#38
0W
#39
b00000000000000000000000001001000 $
b01001000 2
1W
#40
0W
#41
b00000000000000000000000001001100 $
b01001100 2
1W
#42
0W
#43
b00000000000000000000000001010000 $
b01010000 2
1W
#44
0W
#45
b00000000000000000000000001010100 $
b01010100 2
1W
#46
0W
#47
b00000000000000000000000001011000 $
b01011000 2
1W
#48
0W
#49
b00000000000000000000000001011100 $
b01011100 2
1W
#50
0W
#51
b00000000000000000000000001100000 $
b01100000 2
1W
#52
0W
#53
b00000000000000000000000001100100 $
b01100100 2
1W
#54
0W
#55
b00000000000000000000000001101000 $
b01101000 2
1W
#56
0W
#57
b00000000000000000000000001101100 $
b01101100 2
1W
#58
0W
#59
b00000000000000000000000001110000 $
b01110000 2
1W
#60
0W
#61
b00000000000000000000000001110100 $
b01110100 2
1W
#62
0W
#63
b00000000000000000000000001111000 $
b01111000 2
1W
#64
0W
#65
b00000000000000000000000001111100 $
b01111100 2
1W
#66
0W
#67
b00000000000000000000000010000000 $
b10000000 2
1W
#68
0W
#69
b00000000000000000000000010000100 $
b10000100 2
1W
#70
0W
#71
b00000000000000000000000010001000 $
b10001000 2
1W
#72
0W
#73
b00000000000000000000000010001100 $
b10001100 2
1W
#74
0W
#75
b00000000000000000000000010010000 $
b10010000 2
1W
#76
0W
#77
b00000000000000000000000010010100 $
b10010100 2
1W
#78
0W
#79
b00000000000000000000000010011000 $
b10011000 2
1W
#80
0W
#81
b00000000000000000000000010011100 $
b10011100 2
1W
#82
0W
#83
b00000000000000000000000010100000 $
b10100000 2
1W
#84
0W
#85
b00000000000000000000000010100100 $
b10100100 2
1W
#86
0W
#87
b00000000000000000000000010101000 $
b10101000 2
1W
#88
0W
#89
b00000000000000000000000010101100 $
b10101100 2
1W
#90
0W
#91
b00000000000000000000000010110000 $
b10110000 2
1W
#92
0W
#93
b00000000000000000000000010110100 $
b10110100 2
1W
#94
0W
#95
b00000000000000000000000010111000 $
b10111000 2
1W
#96
0W
#97
b00000000000000000000000010111100 $
b10111100 2
1W
#98
0W
#99
b00000000000000000000000011000000 $
b11000000 2
1W
#100
0W
#101
b00000000000000000000000011000100 $
b11000100 2
1W
#102
0W
#103
b00000000000000000000000011001000 $
b11001000 2
1W
#104
0W
#105
b00000000000000000000000011001100 $
b11001100 2
1W
#106
0W
#107
b00000000000000000000000011010000 $
b11010000 2
1W
#108
0W
#109
b00000000000000000000000011010100 $
b11010100 2
1W
#110
0W
#111
b00000000000000000000000011011000 $
b11011000 2
1W
#112
0W
#113
b00000000000000000000000011011100 $
b11011100 2
1W
#114
0W
#115
b00000000000000000000000011100000 $
b11100000 2
1W
#116
0W
#117
b00000000000000000000000011100100 $
b11100100 2
1W
#118
0W
#119
b00000000000000000000000011101000 $
b11101000 2
1W
#120
0W
#121
b00000000000000000000000011101100 $
b11101100 2
1W
#122
0W
#123
b00000000000000000000000011110000 $
b11110000 2
1W
#124
0W
#125
b00000000000000000000000011110100 $
b11110100 2
1W
#126
0W
#127
b00000000000000000000000011111000 $
b11111000 2
1W
#128
0W
#129
b00000000000000000000000011111100 $
b11111100 2
1W
#130
0W
#131
b00000000000000000000000100000000 $
b00000000000000000000000011111111 %
0'
1(
1*
b00000000000000000000000011111111 -
b00001111111100000000001100010011 .
b00000000000000000000000011111111 0
b00000000 2
b11111 4
b00110 5
1W
#132
0W
#133
b00000000000000000000000100000100 $
b00000000000000000000000000000000 %
1'
b00000000000000000000000000000000 -
b00000000000000000000010100010011 .
b00000000000000000000000000000000 0
b00000100 2
b00000 4
b01010 5
1W
#134
0W
#135
b00000000000000000000000100001000 $
b00000000000000000000010110010011 .
b00001000 2
b01011 5
1W
#136
0W
#137
b00000000000000000000000100001100 $
b00000000000001011000010100010011 .
b00001100 2
b01011 3
b01010 5
b00000000000000000000000000000000 B
1W
#138
0W
#139
b00000000000000000000000100010000 $
b00000000000000000000000000000001 %
0'
b00000000000000000000000000000001 -
b00000000000101011000010110010011 .
b00000000000000000000000000000001 0
b00010000 2
b00001 4
b01011 5
1W
#140
0W
#141
b00000000000000000000000100010100 $
b11111111111111111111111111100110 %
1'
0(
0*
b00000000000000000000000000000000 -
b11111110011001011001110011100011 .
b00000000000000000000000000000000 0
b00010100 2
b00110 4
b11001 5
b00000000000000000000000000000001 B
1W
#142
0W
#143
b00000000000000000000000100011000 $
b11111111111111111111111111100000 %
0'
1)
b00000000000000000000000000000001 +
b00000000000000000000000011111111 ,
b11111111111111111111111100000010 -
b11111110000000110001100000000000 .
b001 /
b00000000000000000000000011111111 0
b001 1
b00011000 2
b00110 3
b00000 4
b10000 5
1W
#144
0W
#145
b00000000000000000000000100011100 $
b00000000000000000000000000000000 %
0)
b00000000000000000000000011111111 +
b00000000000000000000000000000000 ,
b00000000000000000000000011111111 -
b00000000000000000000000000000000 .
b000 /
b00000000000000000000000000000000 0
b000 1
b00011100 2
b00000 3
b00000 5
1W
#146
0W
#147
b00000000000000000000000100100000 $
1'
b00000000000000000000000000000000 +
b00000000000000000000000000000000 -
b00100000 2
1W
#148
0W
#149
b00000000000000000000000100100100 $
b00100100 2
1W
#150
0W
#151
b00000000000000000000000100101000 $
b00101000 2
1W
#152
0W
#153
b00000000000000000000000100101100 $
b00101100 2
1W
#154
0W
#155
b00000000000000000000000100110000 $
b00110000 2
1W
#156
0W
#157
b00000000000000000000000100110100 $
b00110100 2
1W
#158
0W
#159
b00000000000000000000000100111000 $
b00111000 2
1W
#160
0W
#161
b00000000000000000000000100111100 $
b00111100 2
1W
#162
0W
#163
b00000000000000000000000101000000 $
b01000000 2
1W
#164
0W
#165
b00000000000000000000000101000100 $
b01000100 2
1W
#166
0W
#167
b00000000000000000000000101001000 $
b01001000 2
1W
#168
0W
#169
b00000000000000000000000101001100 $
b01001100 2
1W
#170
0W
#171
b00000000000000000000000101010000 $
b01010000 2
1W
#172
0W
#173
b00000000000000000000000101010100 $
b01010100 2
1W
#174
0W
#175
b00000000000000000000000101011000 $
b01011000 2
1W
#176
0W
#177
b00000000000000000000000101011100 $
b01011100 2
1W
#178
0W
#179
b00000000000000000000000101100000 $
b01100000 2
1W
#180
0W
#181
b00000000000000000000000101100100 $
b01100100 2
1W
#182
0W
#183
b00000000000000000000000101101000 $
b01101000 2
1W
#184
0W
#185
b00000000000000000000000101101100 $
b01101100 2
1W
#186
0W
#187
b00000000000000000000000101110000 $
b01110000 2
1W
#188
0W
#189
b00000000000000000000000101110100 $
b01110100 2
1W
#190
0W
#191
b00000000000000000000000101111000 $
b01111000 2
1W
#192
0W
#193
b00000000000000000000000101111100 $
b01111100 2
1W
#194
0W
#195
b00000000000000000000000110000000 $
b10000000 2
1W
#196
0W
#197
b00000000000000000000000110000100 $
b10000100 2
1W
#198
0W
#199
b00000000000000000000000110001000 $
b10001000 2
1W
#200
0W
#201
b00000000000000000000000110001100 $
b10001100 2
1W
#202
0W
#203
b00000000000000000000000110010000 $
b10010000 2
1W
#204
0W
#205
b00000000000000000000000110010100 $
b10010100 2
1W
#206
0W
#207
b00000000000000000000000110011000 $
b10011000 2
1W
#208
0W
#209
b00000000000000000000000110011100 $
b10011100 2
1W
#210
0W
#211
b00000000000000000000000110100000 $
b10100000 2
1W
#212
0W
#213
b00000000000000000000000110100100 $
b10100100 2
1W
#214
0W
#215
b00000000000000000000000110101000 $
b10101000 2
1W
#216
0W
#217
b00000000000000000000000110101100 $
b10101100 2
1W
#218
0W
#219
b00000000000000000000000110110000 $
b10110000 2
1W
#220
0W
#221
b00000000000000000000000110110100 $
b10110100 2
1W
#222
0W
#223
b00000000000000000000000110111000 $
b10111000 2
1W
#224
0W
#225
b00000000000000000000000110111100 $
b10111100 2
1W
#226
0W
#227
b00000000000000000000000111000000 $
b11000000 2
1W
#228
0W
#229
b00000000000000000000000111000100 $
b11000100 2
1W
#230
0W
#231
b00000000000000000000000111001000 $
b11001000 2
1W
#232
0W
#233
b00000000000000000000000111001100 $
b11001100 2
1W
#234
0W
#235
b00000000000000000000000111010000 $
b11010000 2
1W
#236
0W
#237
b00000000000000000000000111010100 $
b11010100 2
1W
#238
0W
#239
b00000000000000000000000111011000 $
b11011000 2
1W
#240
0W
#241
b00000000000000000000000111011100 $
b11011100 2
1W
#242
0W
#243
b00000000000000000000000111100000 $
b11100000 2
1W
#244
0W
#245
b00000000000000000000000111100100 $
b11100100 2
1W
#246
0W
#247
b00000000000000000000000111101000 $
b11101000 2
1W
#248
0W
#249
b00000000000000000000000111101100 $
b11101100 2
1W
#250
0W
#251
b00000000000000000000000111110000 $
b11110000 2
1W
#252
0W
#253
b00000000000000000000000111110100 $
b11110100 2
1W
#254
0W
#255
b00000000000000000000000111111000 $
b11111000 2
1W
#256
0W
#257
b00000000000000000000000111111100 $
b11111100 2
1W
#258
0W
#259
b00000000000000000000001000000000 $
b00000000000000000000000011111111 %
0'
1(
1*
b00000000000000000000000011111111 -
b00001111111100000000001100010011 .
b00000000000000000000000011111111 0
b00000000 2
b11111 4
b00110 5
1W
#260
0W
#261
b00000000000000000000001000000100 $
b00000000000000000000000000000000 %
1'
b00000000000000000000000000000000 -
b00000000000000000000010100010011 .
b00000000000000000000000000000000 0
b00000100 2
b00000 4
b01010 5
1W
#262
0W
#263
b00000000000000000000001000001000 $
b00000000000000000000010110010011 .
b00001000 2
b01011 5
1W
#264
0W
#265
b00000000000000000000001000001100 $
b00000000000001011000010100010011 .
b00001100 2
b01011 3
b01010 5
b00000000000000000000000000000000 B
1W
#266
0W
#267
b00000000000000000000001000010000 $
b00000000000000000000000000000001 %
0'
b00000000000000000000000000000001 -
b00000000000101011000010110010011 .
b00000000000000000000000000000001 0
b00010000 2
b00001 4
b01011 5
1W
#268
0W
#269
b00000000000000000000001000010100 $
b11111111111111111111111111100110 %
1'
0(
0*
b00000000000000000000000000000000 -
b11111110011001011001110011100011 .
b00000000000000000000000000000000 0
b00010100 2
b00110 4
b11001 5
b00000000000000000000000000000001 B
1W
#270
0W
#271
b00000000000000000000001000011000 $
b11111111111111111111111111100000 %
0'
1)
b00000000000000000000000000000001 +
b00000000000000000000000011111111 ,
b11111111111111111111111100000010 -
b11111110000000110001100000000000 .
b001 /
b00000000000000000000000011111111 0
b001 1
b00011000 2
b00110 3
b00000 4
b10000 5
1W
#272
0W
#273
b00000000000000000000001000011100 $
b00000000000000000000000000000000 %
0)
b00000000000000000000000011111111 +
b00000000000000000000000000000000 ,
b00000000000000000000000011111111 -
b00000000000000000000000000000000 .
b000 /
b00000000000000000000000000000000 0
b000 1
b00011100 2
b00000 3
b00000 5
1W
#274
0W
#275
b00000000000000000000001000100000 $
1'
b00000000000000000000000000000000 +
b00000000000000000000000000000000 -
b00100000 2
1W
#276
0W
#277
b00000000000000000000001000100100 $
b00100100 2
1W
#278
0W
#279
b00000000000000000000001000101000 $
b00101000 2
1W
#280
0W
#281
b00000000000000000000001000101100 $
b00101100 2
1W
#282
0W
#283
b00000000000000000000001000110000 $
b00110000 2
1W
#284
0W
#285
b00000000000000000000001000110100 $
b00110100 2
1W
#286
0W
#287
b00000000000000000000001000111000 $
b00111000 2
1W
#288
0W
#289
b00000000000000000000001000111100 $
b00111100 2
1W
#290
0W
#291
b00000000000000000000001001000000 $
b01000000 2
1W
#292
0W
#293
b00000000000000000000001001000100 $
b01000100 2
1W
#294
0W
#295
b00000000000000000000001001001000 $
b01001000 2
1W
#296
0W
#297
b00000000000000000000001001001100 $
b01001100 2
1W
#298
0W
#299
b00000000000000000000001001010000 $
b01010000 2
1W
#300
0W
#301
b00000000000000000000001001010100 $
b01010100 2
1W
#302
0W
#303
b00000000000000000000001001011000 $
b01011000 2
1W
#304
0W
#305
b00000000000000000000001001011100 $
b01011100 2
1W
#306
0W
#307
b00000000000000000000001001100000 $
b01100000 2
1W
#308
0W
#309
b00000000000000000000001001100100 $
b01100100 2
1W
#310
0W
#311
b00000000000000000000001001101000 $
b01101000 2
1W
#312
0W
#313
b00000000000000000000001001101100 $
b01101100 2
1W
#314
0W
#315
b00000000000000000000001001110000 $
b01110000 2
1W
#316
0W
#317
b00000000000000000000001001110100 $
b01110100 2
1W
#318
0W
#319
b00000000000000000000001001111000 $
b01111000 2
1W
#320
0W
#321
b00000000000000000000001001111100 $
b01111100 2
1W
#322
0W
#323
b00000000000000000000001010000000 $
b10000000 2
1W
#324
0W
#325
b00000000000000000000001010000100 $
b10000100 2
1W
#326
0W
#327
b00000000000000000000001010001000 $
b10001000 2
1W
#328
0W
#329
b00000000000000000000001010001100 $
b10001100 2
1W
#330
0W
#331
b00000000000000000000001010010000 $
b10010000 2
1W
#332
0W
#333
b00000000000000000000001010010100 $
b10010100 2
1W
#334
0W
#335
b00000000000000000000001010011000 $
b10011000 2
1W
#336
0W
#337
b00000000000000000000001010011100 $
b10011100 2
1W
#338
0W
#339
b00000000000000000000001010100000 $
b10100000 2
1W
#340
0W
#341
b00000000000000000000001010100100 $
b10100100 2
1W
#342
0W
#343
b00000000000000000000001010101000 $
b10101000 2
1W
#344
0W
#345
b00000000000000000000001010101100 $
b10101100 2
1W
#346
0W
#347
b00000000000000000000001010110000 $
b10110000 2
1W
#348
0W
#349
b00000000000000000000001010110100 $
b10110100 2
1W
#350
0W
#351
b00000000000000000000001010111000 $
b10111000 2
1W
#352
0W
#353
b00000000000000000000001010111100 $
b10111100 2
1W
#354
0W
#355
b00000000000000000000001011000000 $
b11000000 2
1W
#356
0W
#357
b00000000000000000000001011000100 $
b11000100 2
1W
#358
0W
#359
b00000000000000000000001011001000 $
b11001000 2
1W
#360
0W
#361
b00000000000000000000001011001100 $
b11001100 2
1W
#362
0W
#363
b00000000000000000000001011010000 $
b11010000 2
1W
#364
0W
#365
b00000000000000000000001011010100 $
b11010100 2
1W
#366
0W
#367
b00000000000000000000001011011000 $
b11011000 2
1W
#368
0W
#369
b00000000000000000000001011011100 $
b11011100 2
1W
#370
0W
#371
b00000000000000000000001011100000 $
b11100000 2
1W
#372
0W
#373
b00000000000000000000001011100100 $
b11100100 2
1W
#374
0W
#375
b00000000000000000000001011101000 $
b11101000 2
1W
#376
0W
#377
b00000000000000000000001011101100 $
b11101100 2
1W
#378
0W
#379
b00000000000000000000001011110000 $
b11110000 2
1W
#380
0W
#381
b00000000000000000000001011110100 $
b11110100 2
1W
#382
0W
#383
b00000000000000000000001011111000 $
b11111000 2
1W
#384
0W
#385
b00000000000000000000001011111100 $
b11111100 2
1W
#386
0W
